Workbook

Sheet Hoja1
A1: ano_eje | B1: exp_siaf | C1: ESTADO | D1: TIPO_BIEN | E1: NRO_CERTIFICA_SIAF | F1: NRO_ORDEN | G1: CENTRO_COSTO | H1: NOMBRE_DEPEND | I1: CODIGO_TAREA | J1: nombre_tarea | K1: GRUPO_BIEN | L1: CLASE_BIEN | M1: FAMILIA_BIEN | N1: ITEM_BIEN | O1: NOMBRE_ITEM | P1: NOMBRE | Q1: CANTIDAD_UNITARIO | R1: PRECIO_UNIT | S1: NRO_RUC | T1: NOMBRE_PROV | U1: fuente_financ | V1: nombre_ff | W1: clasificador | X1: NOMBRE_CLASIF | Y1: sec_func | Z1: prod_pry | AA1: monto_nacional | AB1: FECHA_DEVENGADO
A2: 2026 | B2: 1527 | C2: 2 | D2: B | E2: 1124 | F2: 231 | G2: 94.01 | H2: ORGANO DE CONTROL INSTITUCIONAL | I2: 90 | J2: REALIZACIÓN DE SERVICIOS DE CONTROL RELACIONADO | K2: 71 | L2: 72 | M2: 5 | N2: 224 | O2: PAPEL BOND 80 G TAMAÑO A4 | P2: EMPAQUE X 500 | Q2: 50 | R2: 12.98 | S2: 20609592789 | T2: STCASMAE.I.R.L. | U2: 00 | V2: =VLOOKUP(U2,d_ff!A$1:B$5,2,0) -> 00: RECURSOS ORDINARIOS | W2: 2.3. 1 5. 1 2 | X2: =VLOOKUP(W2,d_clasif!B$1:C$1529,2,0) -> 2.3. 1 5. 1 2: PAPELERIA EN GENERAL, UTILES Y MATERIALES DE OFICINA | Y2: 45 | Z2: Cadenas Presupuestal: Siaf/Ord: 1527/231 | AA2: 649 | AB2: 46185
A3: 2026 | B3: 1527 | C3: 2 | D3: B | E3: 1124 | F3: 231 | G3: 94.01 | H3: ORGANO DE CONTROL INSTITUCIONAL | I3: 91 | J3: REALIZACIÓN DE SERVICIO DE CONTROL SIMULTANEO | K3: 71 | L3: 72 | M3: 5 | N3: 224 | O3: PAPEL BOND 80 G TAMAÑO A4 | P3: EMPAQUE X 500 | Q3: 50 | R3: 12.98 | S3: 20609592789 | T3: STCASMAE.I.R.L. | U3: 00 | V3: =VLOOKUP(U3,d_ff!A$1:B$5,2,0) -> 00: RECURSOS ORDINARIOS | W3: 2.3. 1 5. 1 2 | X3: =VLOOKUP(W3,d_clasif!B$1:C$1529,2,0) -> 2.3. 1 5. 1 2: PAPELERIA EN GENERAL, UTILES Y MATERIALES DE OFICINA | Y3: 45 | Z3: Cadenas Presupuestal: Siaf/Ord: 1527/231 | AA3: 649 | AB3: 46185
A4: 2026 | B4: 818 | C4: 2 | D4: B | E4: 586 | F4: 106 | G4: 94.02.02 | H4: OFICINA DE ASESORIA JURIDICA | I4: 14 | J4: ATENCIÓN DE ACCIONES DE ASESORAMIENTO JURÍDICO | K4: 71 | L4: 85 | M4: 8 | N4: 26 | O4: GRAPA 26/6 X 5000 | P4: UNIDAD | Q4: 100 | R4: 3.54 | S4: 20600944348 | T4: DISTRIBUIDORA UNIVERSAL ICA E.I.R.L | U4: 00 | V4: =VLOOKUP(U4,d_ff!A$1:B$5,2,0) -> 00: RECURSOS ORDINARIOS | W4: 2.3. 1 5. 1 2 | X4: =VLOOKUP(W4,d_clasif!B$1:C$1529,2,0) -> 2.3. 1 5. 1 2: PAPELERIA EN GENERAL, UTILES Y MATERIALES DE OFICINA | Y4: 43 | Z4: Cadenas Presupuestal: Siaf/Ord: 818/106 | AA4: 354 | AB4: 46164
A5: 2026 | B5: 1527 | C5: 2 | D5: B | E5: 1124 | F5: 231 | G5: 94.02.02 | H5: OFICINA DE ASESORIA JURIDICA | I5: 14 | J5: ATENCIÓN DE ACCIONES DE ASESORAMIENTO JURÍDICO | K5: 71 | L5: 72 | M5: 5 | N5: 224 | O5: PAPEL BOND 80 G TAMAÑO A4 | P5: EMPAQUE X 500 | Q5: 140 | R5: 12.98 | S5: 20609592789 | T5: STCASMAE.I.R.L. | U5: 00 | V5: =VLOOKUP(U5,d_ff!A$1:B$5,2,0) -> 00: RECURSOS ORDINARIOS | W5: 2.3. 1 5. 1 2 | X5: =VLOOKUP(W5,d_clasif!B$1:C$1529,2,0) -> 2.3. 1 5. 1 2: PAPELERIA EN GENERAL, UTILES Y MATERIALES DE OFICINA | Y5: 43 | Z5: Cadenas Presupuestal: Siaf/Ord: 1527/231 | AA5: 1817.2 | AB5: 46185
A6: 2026 | B6: 1046 | C6: 2 | D6: B | E6: 771 | F6: 143 | G6: 94.02.02 | H6: OFICINA DE ASESORIA JURIDICA | I6: 14 | J6: ATENCIÓN DE ACCIONES DE ASESORAMIENTO JURÍDICO | K6: 71 | L6: 85 | M6: 5 | N6: 58 | O6: CLIP DE METAL 30 mm APROX. X 100 | P6: UNIDAD | Q6: 30 | R6: 2.8 | S6: 10704570894 | T6: DIAZ CORDERO NICOLL FABIOLA | U6: 00 | V6: =VLOOKUP(U6,d_ff!A$1:B$5,2,0) -> 00: RECURSOS ORDINARIOS | W6: 2.3. 1 5. 1 2 | X6: =VLOOKUP(W6,d_clasif!B$1:C$1529,2,0) -> 2.3. 1 5. 1 2: PAPELERIA EN GENERAL, UTILES Y MATERIALES DE OFICINA | Y6: 43 | Z6: Cadenas Presupuestal: Siaf/Ord: 1046/143 | AA6: 84 | AB6: 46176
A7: 2026 | B7: 818 | C7: 2 | D7: B | E7: 586 | F7: 106 | G7: 94.02.02 | H7: OFICINA DE ASESORIA JURIDICA | I7: 14 | J7: ATENCIÓN DE ACCIONES DE ASESORAMIENTO JURÍDICO | K7: 50 | L7: 33 | M7: 25 | N7: 45 | O7: CINTA DE PLASTICO ADHESIVA PARA EMBALAJE 2 in X 110 yd | P7: UNIDAD | Q7: 50 | R7: 11.799971 | S7: 20600944348 | T7: DISTRIBUIDORA UNIVERSAL ICA E.I.R.L | U7: 00 | V7: =VLOOKUP(U7,d_ff!A$1:B$5,2,0) -> 00: RECURSOS ORDINARIOS | W7: 2.3. 1 5. 1 2 | X7: =VLOOKUP(W7,d_clasif!B$1:C$1529,2,0) -> 2.3. 1 5. 1 2: PAPELERIA EN GENERAL, UTILES Y MATERIALES DE OFICINA | Y7: 43 | Z7: Cadenas Presupuestal: Siaf/Ord: 818/106 | AA7: 590 | AB7: 46164
A8: 2026 | B8: 818 | C8: 2 | D8: B | E8: 586 | F8: 106 | G8: 94.02.02 | H8: OFICINA DE ASESORIA JURIDICA | I8: 14 | J8: ATENCIÓN DE ACCIONES DE ASESORAMIENTO JURÍDICO | K8: 71 | L8: 6 | M8: 4 | N8: 4 | O8: FOLDER MANILA TAMAÑO A4 | P8: UNIDAD | Q8: 600 | R8: 0.531 | S8: 20600944348 | T8: DISTRIBUIDORA UNIVERSAL ICA E.I.R.L | U8: 00 | V8: =VLOOKUP(U8,d_ff!A$1:B$5,2,0) -> 00: RECURSOS ORDINARIOS | W8: 2.3. 1 5. 1 2 | X8: =VLOOKUP(W8,d_clasif!B$1:C$1529,2,0) -> 2.3. 1 5. 1 2: PAPELERIA EN GENERAL, UTILES Y MATERIALES DE OFICINA | Y8: 43 | Z8: Cadenas Presupuestal: Siaf/Ord: 818/106 | AA8: 318.6 | AB8: 46164
A9: 2026 | B9: 818 | C9: 2 | D9: B | E9: 586 | F9: 106 | G9: 94.02.02 | H9: OFICINA DE ASESORIA JURIDICA | I9: 14 | J9: ATENCIÓN DE ACCIONES DE ASESORAMIENTO JURÍDICO | K9: 71 | L9: 6 | M9: 5 | N9: 13 | O9: FOLDER DE PLASTICO TAMAÑO A4 CON TAPA TRANSPARENTE | P9: UNIDAD | Q9: 25 | R9: 1.59303 | S9: 20600944348 | T9: DISTRIBUIDORA UNIVERSAL ICA E.I.R.L | U9: 00 | V9: =VLOOKUP(U9,d_ff!A$1:B$5,2,0) -> 00: RECURSOS ORDINARIOS | W9: 2.3. 1 5. 1 2 | X9: =VLOOKUP(W9,d_clasif!B$1:C$1529,2,0) -> 2.3. 1 5. 1 2: PAPELERIA EN GENERAL, UTILES Y MATERIALES DE OFICINA | Y9: 43 | Z9: Cadenas Presupuestal: Siaf/Ord: 818/106 | AA9: 39.83 | AB9: 46164
A10: 2026 | B10: 818 | C10: 2 | D10: B | E10: 586 | F10: 106 | G10: 94.02.02 | H10: OFICINA DE ASESORIA JURIDICA | I10: 14 | J10: ATENCIÓN DE ACCIONES DE ASESORAMIENTO JURÍDICO | K10: 71 | L10: 6 | M10: 6 | N10: 44 | O10: FORRO DE PLASTICO TRANSPARENTE TAMAÑO OFICIO X 5 m | P10: UNIDAD | Q10: 25 | R10: 8.118395 | S10: 20600944348 | T10: DISTRIBUIDORA UNIVERSAL ICA E.I.R.L | U10: 00 | V10: =VLOOKUP(U10,d_ff!A$1:B$5,2,0) -> 00: RECURSOS ORDINARIOS | W10: 2.3. 1 5. 1 2 | X10: =VLOOKUP(W10,d_clasif!B$1:C$1529,2,0) -> 2.3. 1 5. 1 2: PAPELERIA EN GENERAL, UTILES Y MATERIALES DE OFICINA | Y10: 43 | Z10: Cadenas Presupuestal: Siaf/Ord: 818/106 | AA10: 202.96 | AB10: 46164
A11: 2026 | B11: 818 | C11: 2 | D11: B | E11: 586 | F11: 106 | G11: 94.02.02 | H11: OFICINA DE ASESORIA JURIDICA | I11: 14 | J11: ATENCIÓN DE ACCIONES DE ASESORAMIENTO JURÍDICO | K11: 71 | L11: 72 | M11: 3 | N11: 227 | O11: CUADERNO DOBLE ESPIRAL CUADRICULADO TAMAÑO A4 X 200 HOJAS | P11: UNIDAD | Q11: 17 | R11: 34.81 | S11: 20600944348 | T11: DISTRIBUIDORA UNIVERSAL ICA E.I.R.L | U11: 00 | V11: =VLOOKUP(U11,d_ff!A$1:B$5,2,0) -> 00: RECURSOS ORDINARIOS | W11: 2.3. 1 5. 1 2 | X11: =VLOOKUP(W11,d_clasif!B$1:C$1529,2,0) -> 2.3. 1 5. 1 2: PAPELERIA EN GENERAL, UTILES Y MATERIALES DE OFICINA | Y11: 43 | Z11: Cadenas Presupuestal: Siaf/Ord: 818/106 | AA11: 591.77 | AB11: 46164
A12: 2026 | B12: 1046 | C12: 2 | D12: B | E12: 771 | F12: 143 | G12: 94.02.02 | H12: OFICINA DE ASESORIA JURIDICA | I12: 14 | J12: ATENCIÓN DE ACCIONES DE ASESORAMIENTO JURÍDICO | K12: 71 | L12: 85 | M12: 5 | N12: 46 | O12: CLIP DE METAL 50 mm X 100 | P12: UNIDAD | Q12: 24 | R12: 5 | S12: 10704570894 | T12: DIAZ CORDERO NICOLL FABIOLA | U12: 00 | V12: =VLOOKUP(U12,d_ff!A$1:B$5,2,0) -> 00: RECURSOS ORDINARIOS | W12: 2.3. 1 5. 1 2 | X12: =VLOOKUP(W12,d_clasif!B$1:C$1529,2,0) -> 2.3. 1 5. 1 2: PAPELERIA EN GENERAL, UTILES Y MATERIALES DE OFICINA | Y12: 43 | Z12: Cadenas Presupuestal: Siaf/Ord: 1046/143 | AA12: 120 | AB12: 46176
A13: 2026 | B13: 818 | C13: 2 | D13: B | E13: 586 | F13: 106 | G13: 94.02.02 | H13: OFICINA DE ASESORIA JURIDICA | I13: 252 | J13: ATENCIÓN DE ACCIONES DE DEFENSA LEGAL DE LOS INTERESES INSTITUCIONALES EN PROCESOS JUDICIALES | K13: 71 | L13: 50 | M13: 11 | N13: 88 | O13: ENGRAPADOR TIPO ALICATE PARA 50 HOJAS APROX. | P13: UNIDAD | Q13: 9 | R13: 44.25 | S13: 20600944348 | T13: DISTRIBUIDORA UNIVERSAL ICA E.I.R.L | U13: 00 | V13: =VLOOKUP(U13,d_ff!A$1:B$5,2,0) -> 00: RECURSOS ORDINARIOS | W13: 2.3. 1 5. 1 2 | X13: =VLOOKUP(W13,d_clasif!B$1:C$1529,2,0) -> 2.3. 1 5. 1 2: PAPELERIA EN GENERAL, UTILES Y MATERIALES DE OFICINA | Y13: 43 | Z13: Cadenas Presupuestal: Siaf/Ord: 818/106 | AA13: 398.25 | AB13: 46164
A14: 2026 | B14: 818 | C14: 2 | D14: B | E14: 586 | F14: 106 | G14: 94.02.02 | H14: OFICINA DE ASESORIA JURIDICA | I14: 252 | J14: ATENCIÓN DE ACCIONES DE DEFENSA LEGAL DE LOS INTERESES INSTITUCIONALES EN PROCESOS JUDICIALES | K14: 71 | L14: 60 | M14: 4 | N14: 112 | O14: LAPIZ NEGRO GRADO 2B CON BORRADOR | P14: UNIDAD | Q14: 50 | R14: 0.460203 | S14: 20600944348 | T14: DISTRIBUIDORA UNIVERSAL ICA E.I.R.L | U14: 00 | V14: =VLOOKUP(U14,d_ff!A$1:B$5,2,0) -> 00: RECURSOS ORDINARIOS | W14: 2.3. 1 5. 1 2 | X14: =VLOOKUP(W14,d_clasif!B$1:C$1529,2,0) -> 2.3. 1 5. 1 2: PAPELERIA EN GENERAL, UTILES Y MATERIALES DE OFICINA | Y14: 43 | Z14: Cadenas Presupuestal: Siaf/Ord: 818/106 | AA14: 23.01 | AB14: 46164
A15: 2026 | B15: 1527 | C15: 2 | D15: B | E15: 1124 | F15: 231 | G15: 94.02.02 | H15: OFICINA DE ASESORIA JURIDICA | I15: 252 | J15: ATENCIÓN DE ACCIONES DE DEFENSA LEGAL DE LOS INTERESES INSTITUCIONALES EN PROCESOS JUDICIALES | K15: 71 | L15: 72 | M15: 5 | N15: 224 | O15: PAPEL BOND 80 G TAMAÑO A4 | P15: EMPAQUE X 500 | Q15: 28 | R15: 12.98 | S15: 20609592789 | T15: STCASMAE.I.R.L. | U15: 00 | V15: =VLOOKUP(U15,d_ff!A$1:B$5,2,0) -> 00: RECURSOS ORDINARIOS | W15: 2.3. 1 5. 1 2 | X15: =VLOOKUP(W15,d_clasif!B$1:C$1529,2,0) -> 2.3. 1 5. 1 2: PAPELERIA EN GENERAL, UTILES Y MATERIALES DE OFICINA | Y15: 43 | Z15: Cadenas Presupuestal: Siaf/Ord: 1527/231 | AA15: 363.44 | AB15: 46185
... A2511: 2026 | B2511: 165 | C2511: 2 | D2511: S | E2511: 86 | F2511: 70 | G2511: 94.02.02 | H2511: OFICINA DE ASESORIA JURIDICA | I2511: 252 | J2511: ATENCIÓN DE ACCIONES DE DEFENSA LEGAL DE LOS INTERESES INSTITUCIONALES EN PROCESOS JUDICIALES | K2511: 7 | L2511: 5 | M2511: 4 | N2511: 43 | O2511: SERVICIO ESPECIALIZADO EN MATERIA LEGAL | P2511: SERVICIO | Q2511: 10500 | R2511: 1 | S2511: 10436811123 | T2511: BOCANGEL MAMANI HANS ENDELBERTH | U2511: 00 | V2511: =VLOOKUP(U2511,d_ff!A$1:B$5,2,0) -> 00: RECURSOS ORDINARIOS | W2511: 2.3. 2 9. 1 1 | X2511: =VLOOKUP(W2511,d_clasif!B$1:C$1529,2,0) -> 2.3. 2 9. 1 1: LOCACION DE SERVICIOS REALIZADOS POR PERSONAS NATURALES RELACIONADAS AL ROL DE LA ENTIDAD | Y2511: 43 | Z2511: Cadenas Presupuestal: 94=>9001=>3999999=>5000004=>22=>6=>8=>1=>12=>27 Siaf/Ord: 165/70 | AA2511: 3465 | AB2511: 46094
A2512: 2026 | B2512: 158 | C2512: 2 | D2512: S | E2512: 89 | F2512: 58 | G2512: 94.01 | H2512: ORGANO DE CONTROL INSTITUCIONAL | I2512: 90 | J2512: REALIZACIÓN DE SERVICIOS DE CONTROL RELACIONADO | K2512: 7 | L2512: 11 | M2512: 38 | N2512: 6361 | O2512: SERVCIO ESPECIALIZADO EN CONTROL GUBERNAMENTAL | P2512: SERVICIO | Q2512: 9000 | R2512: 1 | S2512: 10700772654 | T2512: CUADROS LAGOS IZAMAR ROSALI | U2512: 00 | V2512: =VLOOKUP(U2512,d_ff!A$1:B$5,2,0) -> 00: RECURSOS ORDINARIOS | W2512: 2.3. 2 9. 1 1 | X2512: =VLOOKUP(W2512,d_clasif!B$1:C$1529,2,0) -> 2.3. 2 9. 1 1: LOCACION DE SERVICIOS REALIZADOS POR PERSONAS NATURALES RELACIONADAS AL ROL DE LA ENTIDAD | Y2512: 45 | Z2512: Cadenas Presupuestal: 94=>9001=>3999999=>5000006=>22=>6=>12=>1=>8=>27 Siaf/Ord: 158/58 | AA2512: 2970 | AB2512: 46094
A2513: 2026 | B2513: 161 | C2513: 2 | D2513: S | E2513: 132 | F2513: 107 | G2513: 94.02.19 | H2513: ESCUELA DE POSGRADO | I2513: 272 | J2513: IMPLEMENTACIÓN DEL PROCESO DE ADMISIÒN EN LA ESCUELA DE POSGRADO | K2513: 50 | L2513: 1 | M2513: 5 | N2513: 561 | O2513: SERVICIO DE IMPRESIONES EN GENERAL | P2513: SERVICIO | Q2513: 43740 | R2513: 1 | S2513: 10403020473 | T2513: MENDOZA TAPAHUASCO BERTHA | U2513: 09 | V2513: =VLOOKUP(U2513,d_ff!A$1:B$5,2,0) -> 09: RECURSOS DIRECTAMENTE RECAUDADOS | W2513: 2.3. 2 7.11 6 | X2513: =VLOOKUP(W2513,d_clasif!B$1:C$1529,2,0) -> 2.3. 2 7.11 6: SERVICIO DE IMPRESIONES, ENCUADERNACION Y EMPASTADO | Y2513: 50 | Z2513: Cadenas Presupuestal: 94=>9002=>3999999=>5000670=>22=>48=>110=>1=>589=>1 Siaf/Ord: 161/107 | AA2513: 43740 | AB2513: 46100
A2514: 2026 | B2514: 160 | C2514: 2 | D2514: S | E2514: 134 | F2514: 109 | G2514: 94.02.19 | H2514: ESCUELA DE POSGRADO | I2514: 272 | J2514: IMPLEMENTACIÓN DEL PROCESO DE ADMISIÒN EN LA ESCUELA DE POSGRADO | K2514: 70 | L2514: 10 | M2514: 2 | N2514: 185 | O2514: SERVICIO DE ELABORACION DE SPOT CON CONTENIDO AUDIOVISUAL | P2514: SERVICIO | Q2514: 10000 | R2514: 1 | S2514: 10427285656 | T2514: PIMENTEL INFANTE VICTOR HUGO | U2514: 09 | V2514: =VLOOKUP(U2514,d_ff!A$1:B$5,2,0) -> 09: RECURSOS DIRECTAMENTE RECAUDADOS | W2514: 2.3. 2 2. 4 1 | X2514: =VLOOKUP(W2514,d_clasif!B$1:C$1529,2,0) -> 2.3. 2 2. 4 1: SERVICIO DE PUBLICIDAD | Y2514: 50 | Z2514: Cadenas Presupuestal: 94=>9002=>3999999=>5000670=>22=>48=>110=>1=>589=>27 Siaf/Ord: 160/109 | AA2514: 10000 | AB2514: 46086
A2515: 2026 | B2515: 282 | C2515: 2 | D2515: S | E2515: 171 | F2515: 129 | G2515: 94.02.19 | H2515: ESCUELA DE POSGRADO | I2515: 35 | J2515: IMPLEMENTACION DEL PROCESO DE ENSEÑANZA A LOS MAESTRANDO | K2515: 7 | L2515: 11 | M2515: 38 | N2515: 2839 | O2515: SERVICIO ESPECIALIZADO EN GESTION DE LA INFORMACION | P2515: SERVICIO | Q2515: 5100 | R2515: 1 | S2515: 10746907074 | T2515: TACURI YUPANQUI LEONEL | U2515: 09 | V2515: =VLOOKUP(U2515,d_ff!A$1:B$5,2,0) -> 09: RECURSOS DIRECTAMENTE RECAUDADOS | W2515: 2.3. 2 7.14 98 | X2515: =VLOOKUP(W2515,d_clasif!B$1:C$1529,2,0) -> 2.3. 2 7.14 98: OTROS SERVICIOS TECNICOS Y PROFESIONALES DESARROLLADOS POR PERSONAS NATURALES | Y2515: 50 | Z2515: Cadenas Presupuestal: 94=>9002=>3999999=>5000670=>22=>48=>110=>1=>589=>27 Siaf/Ord: 282/129 | AA2515: 1683 | AB2515: 46111
A2516: 2026 | B2516: 283 | C2516: 2 | D2516: S | E2516: 175 | F2516: 132 | G2516: 94.02.19 | H2516: ESCUELA DE POSGRADO | I2516: 35 | J2516: IMPLEMENTACION DEL PROCESO DE ENSEÑANZA A LOS MAESTRANDO | K2516: 7 | L2516: 5 | M2516: 4 | N2516: 200 | O2516: SERVICIO ESPECIALIZADO EN COMPUTACION | P2516: SERVICIO | Q2516: 5100 | R2516: 1 | S2516: 10461009056 | T2516: CANCHARI GUTIERREZ REYZA JUDITH | U2516: 09 | V2516: =VLOOKUP(U2516,d_ff!A$1:B$5,2,0) -> 09: RECURSOS DIRECTAMENTE RECAUDADOS | W2516: 2.3. 2 7.14 98 | X2516: =VLOOKUP(W2516,d_clasif!B$1:C$1529,2,0) -> 2.3. 2 7.14 98: OTROS SERVICIOS TECNICOS Y PROFESIONALES DESARROLLADOS POR PERSONAS NATURALES | Y2516: 50 | Z2516: Cadenas Presupuestal: 94=>9002=>3999999=>5000670=>22=>48=>110=>1=>589=>27 Siaf/Ord: 283/132 | AA2516: 1683 | AB2516: 46110
A2517: 2026 | B2517: 269 | C2517: 2 | D2517: S | E2517: 168 | F2517: 128 | G2517: 94.02.19 | H2517: ESCUELA DE POSGRADO | I2517: 35 | J2517: IMPLEMENTACION DEL PROCESO DE ENSEÑANZA A LOS MAESTRANDO | K2517: 7 | L2517: 11 | M2517: 38 | N2517: 279 | O2517: SERVICIO DE DOCENCIA | P2517: SERVICIO | Q2517: 6400 | R2517: 1 | S2517: 10070991905 | T2517: PAREDES INFANZON JELIO | U2517: 09 | V2517: =VLOOKUP(U2517,d_ff!A$1:B$5,2,0) -> 09: RECURSOS DIRECTAMENTE RECAUDADOS | W2517: 2.3. 2 9. 1 1 | X2517: =VLOOKUP(W2517,d_clasif!B$1:C$1529,2,0) -> 2.3. 2 9. 1 1: LOCACION DE SERVICIOS REALIZADOS POR PERSONAS NATURALES RELACIONADAS AL ROL DE LA ENTIDAD | Y2517: 50 | Z2517: Cadenas Presupuestal: 94=>9002=>3999999=>5000670=>22=>48=>110=>1=>589=>27 Siaf/Ord: 269/128 | AA2517: 6400 | AB2517: 46090
A2518: 2026 | B2518: 287 | C2518: 2 | D2518: S | E2518: 183 | F2518: 135 | G2518: 94.02.19 | H2518: ESCUELA DE POSGRADO | I2518: 274 | J2518: REALIZACIÓN DEL FUNCIONAMIENTO DE LA ESCUELA DE POSGRADO EN LAS ACTIVIDADES ADMINISTRATIVAS | K2518: 7 | L2518: 11 | M2518: 43 | N2518: 1109 | O2518: SERVICIO DE SEGUIMIENTO DE DOCUMENTOS ADMINISTRATIVOS | P2518: SERVICIO | Q2518: 3400 | R2518: 1 | S2518: 10762496122 | T2518: QUISPE BENDEZU MARCO ANTONIO | U2518: 09 | V2518: =VLOOKUP(U2518,d_ff!A$1:B$5,2,0) -> 09: RECURSOS DIRECTAMENTE RECAUDADOS | W2518: 2.3. 2 9. 1 1 | X2518: =VLOOKUP(W2518,d_clasif!B$1:C$1529,2,0) -> 2.3. 2 9. 1 1: LOCACION DE SERVICIOS REALIZADOS POR PERSONAS NATURALES RELACIONADAS AL ROL DE LA ENTIDAD | Y2518: 50 | Z2518: Cadenas Presupuestal: 94=>9002=>3999999=>5000670=>22=>48=>110=>1=>589=>27 Siaf/Ord: 287/135 | AA2518: 1700 | AB2518: 46111
A2519: 2026 | B2519: 323 | C2519: 2 | D2519: S | E2519: 180 | F2519: 133 | G2519: 94.02.19 | H2519: ESCUELA DE POSGRADO | I2519: 35 | J2519: IMPLEMENTACION DEL PROCESO DE ENSEÑANZA A LOS MAESTRANDO | K2519: 7 | L2519: 11 | M2519: 38 | N2519: 279 | O2519: SERVICIO DE DOCENCIA | P2519: SERVICIO | Q2519: 5760 | R2519: 1 | S2519: 10282898522 | T2519: QUISPE QUISPE JOSE ANTONIO | U2519: 09 | V2519: =VLOOKUP(U2519,d_ff!A$1:B$5,2,0) -> 09: RECURSOS DIRECTAMENTE RECAUDADOS | W2519: 2.3. 2 9. 1 1 | X2519: =VLOOKUP(W2519,d_clasif!B$1:C$1529,2,0) -> 2.3. 2 9. 1 1: LOCACION DE SERVICIOS REALIZADOS POR PERSONAS NATURALES RELACIONADAS AL ROL DE LA ENTIDAD | Y2519: 50 | Z2519: Cadenas Presupuestal: 94=>9002=>3999999=>5000670=>22=>48=>110=>1=>589=>27 Siaf/Ord: 323/133 | AA2519: 5760 | AB2519: 46099
A2520: 2026 | B2520: 559 | C2520: 2 | D2520: S | E2520: 398 | F2520: 277 | G2520: 94.02.19 | H2520: ESCUELA DE POSGRADO | I2520: 35 | J2520: IMPLEMENTACION DEL PROCESO DE ENSEÑANZA A LOS MAESTRANDO | K2520: 7 | L2520: 11 | M2520: 38 | N2520: 279 | O2520: SERVICIO DE DOCENCIA | P2520: SERVICIO | Q2520: 5760 | R2520: 1 | S2520: 10074767031 | T2520: PIMENTEL LLAMOCCA ENRIQUE LUIS | U2520: 09 | V2520: =VLOOKUP(U2520,d_ff!A$1:B$5,2,0) -> 09: RECURSOS DIRECTAMENTE RECAUDADOS | W2520: 2.3. 2 9. 1 1 | X2520: =VLOOKUP(W2520,d_clasif!B$1:C$1529,2,0) -> 2.3. 2 9. 1 1: LOCACION DE SERVICIOS REALIZADOS POR PERSONAS NATURALES RELACIONADAS AL ROL DE LA ENTIDAD | Y2520: 50 | Z2520: Cadenas Presupuestal: 94=>9002=>3999999=>5000670=>22=>48=>110=>1=>589=>27 Siaf/Ord: 559/277 | AA2520: 5760 | AB2520: 46105
A2521: 2026 | B2521: 503 | C2521: 2 | D2521: S | E2521: 362 | F2521: 254 | G2521: 94.02.08.07 | H2521: UNIDAD EJECUTORA DE INVERSIONES | I2521: 381 | J2521: MEJORAM Y AMPLIAC DEL SERV DE GESTION INSTIT EN EL SISTEMA DE VIDEO VIGILANCIA Y CONTROL DE ACCESO DE PERSONAS EN LA CIUDAD UNIVERSITARIA DE LA UNSCH | K2521: 7 | L2521: 5 | M2521: 3 | N2521: 622 | O2521: SERVICIO DE EXAMEN MEDICO OCUPACIONAL | P2521: SERVICIO | Q2521: 2704 | R2521: 1 | S2521: 20608052080 | T2521: EPSS ESPECIALIDADES MEDICAS ONCOLABS E.I.R.L. | U2521: 00 | V2521: =VLOOKUP(U2521,d_ff!A$1:B$5,2,0) -> 00: RECURSOS ORDINARIOS | W2521: 2.6. 2 2. 2 5 | X2521: =VLOOKUP(W2521,d_clasif!B$1:C$1529,2,0) -> 2.6. 2 2. 2 5: COSTO DE CONSTRUCCION POR ADMINISTRACION DIRECTA - SERVICIOS | Y2521: 63 | Z2521: Cadenas Presupuestal: 94=>66=>2534035=>4000040=>22=>48=>10=>1=>37703=>1 Siaf/Ord: 503/254 | AA2521: 2704 | AB2521: 46125
A2522: 2026 | B2522: 582 | C2522: 2 | D2522: S | E2522: 438 | F2522: 293 | G2522: 94.02.08.07 | H2522: UNIDAD EJECUTORA DE INVERSIONES | I2522: 381 | J2522: MEJORAM Y AMPLIAC DEL SERV DE GESTION INSTIT EN EL SISTEMA DE VIDEO VIGILANCIA Y CONTROL DE ACCESO DE PERSONAS EN LA CIUDAD UNIVERSITARIA DE LA UNSCH | K2522: 85 | L2522: 1 | M2522: 7 | N2522: 6 | O2522: SEGURO COMPLEMENTARIO DE TRABAJO DE RIESGO - PENSION | P2522: SERVICIO | Q2522: 639 | R2522: 1 | S2522: 20418896915 | T2522: MAPFRE PERU COMPAÑIA DE SEGUROS Y REASEGUROS | U2522: 00 | V2522: =VLOOKUP(U2522,d_ff!A$1:B$5,2,0) -> 00: RECURSOS ORDINARIOS | W2522: 2.6. 2 2. 2 5 | X2522: =VLOOKUP(W2522,d_clasif!B$1:C$1529,2,0) -> 2.6. 2 2. 2 5: COSTO DE CONSTRUCCION POR ADMINISTRACION DIRECTA - SERVICIOS | Y2522: 63 | Z2522: Cadenas Presupuestal: 94=>66=>2534035=>4000040=>22=>48=>10=>1=>37703=>1 Siaf/Ord: 582/293 | AA2522: 639.49 | AB2522: 46140
A2523: 2026 | B2523: 584 | C2523: 2 | D2523: S | E2523: 439 | F2523: 296 | G2523: 94.02.08.07 | H2523: UNIDAD EJECUTORA DE INVERSIONES | I2523: 381 | J2523: MEJORAM Y AMPLIAC DEL SERV DE GESTION INSTIT EN EL SISTEMA DE VIDEO VIGILANCIA Y CONTROL DE ACCESO DE PERSONAS EN LA CIUDAD UNIVERSITARIA DE LA UNSCH | K2523: 85 | L2523: 1 | M2523: 7 | N2523: 7 | O2523: SEGURO COMPLEMENTARIO DE TRABAJO DE RIESGO - SALUD | P2523: SERVICIO | Q2523: 704 | R2523: 1 | S2523: 20517182673 | T2523: MAPFRE PERU S.A. ENTIDAD PRESTADORA DE SALUD | U2523: 00 | V2523: =VLOOKUP(U2523,d_ff!A$1:B$5,2,0) -> 00: RECURSOS ORDINARIOS | W2523: 2.6. 2 2. 2 5 | X2523: =VLOOKUP(W2523,d_clasif!B$1:C$1529,2,0) -> 2.6. 2 2. 2 5: COSTO DE CONSTRUCCION POR ADMINISTRACION DIRECTA - SERVICIOS | Y2523: 63 | Z2523: Cadenas Presupuestal: 94=>66=>2534035=>4000040=>22=>48=>10=>1=>37703=>1 Siaf/Ord: 584/296 | AA2523: 703.65 | AB2523: 46140
A2524: 2026 | B2524: 373 | C2524: 2 | D2524: S | E2524: 274 | F2524: 198 | G2524: 94.02.08.07 | H2524: UNIDAD EJECUTORA DE INVERSIONES | I2524: 381 | J2524: MEJORAM Y AMPLIAC DEL SERV DE GESTION INSTIT EN EL SISTEMA DE VIDEO VIGILANCIA Y CONTROL DE ACCESO DE PERSONAS EN LA CIUDAD UNIVERSITARIA DE LA UNSCH | K2524: 94 | L2524: 20 | M2524: 3 | N2524: 10 | O2524: ALQUILER DE CAMIONETA | P2524: SERVICIO | Q2524: 2324 | R2524: 1 | S2524: 10485476402 | T2524: FLORES RIVEROS FLOR MARIA | U2524: 00 | V2524: =VLOOKUP(U2524,d_ff!A$1:B$5,2,0) -> 00: RECURSOS ORDINARIOS | W2524: 2.6. 2 2. 2 5 | X2524: =VLOOKUP(W2524,d_clasif!B$1:C$1529,2,0) -> 2.6. 2 2. 2 5: COSTO DE CONSTRUCCION POR ADMINISTRACION DIRECTA - SERVICIOS | Y2524: 63 | Z2524: Cadenas Presupuestal: 94=>66=>2534035=>4000040=>22=>48=>10=>1=>37703=>2 Siaf/Ord: 373/198 | AA2524: 2324 | AB2524: 46118
... A2698: 2026 | B2698: 165 | C2698: 2 | D2698: S | E2698: 86 | F2698: 70 | G2698: 94.02.02 | H2698: OFICINA DE ASESORIA JURIDICA | I2698: 252 | J2698: ATENCIÓN DE ACCIONES DE DEFENSA LEGAL DE LOS INTERESES INSTITUCIONALES EN PROCESOS JUDICIALES | K2698: 7 | L2698: 5 | M2698: 4 | N2698: 43 | O2698: SERVICIO ESPECIALIZADO EN MATERIA LEGAL | P2698: SERVICIO | Q2698: 10500 | R2698: 1 | S2698: 10436811123 | T2698: BOCANGEL MAMANI HANS ENDELBERTH | U2698: 00 | V2698: =VLOOKUP(U2698,d_ff!A$1:B$5,2,0) -> 00: RECURSOS ORDINARIOS | W2698: 2.3. 2 9. 1 1 | X2698: =VLOOKUP(W2698,d_clasif!B$1:C$1529,2,0) -> 2.3. 2 9. 1 1: LOCACION DE SERVICIOS REALIZADOS POR PERSONAS NATURALES RELACIONADAS AL ROL DE LA ENTIDAD | Y2698: 43 | Z2698: Cadenas Presupuestal: 94=>9001=>3999999=>5000004=>22=>6=>8=>1=>12=>27 Siaf/Ord: 165/70 | AA2698: 3465 | AB2698: 46125
A2699: 2026 | B2699: 158 | C2699: 2 | D2699: S | E2699: 89 | F2699: 58 | G2699: 94.01 | H2699: ORGANO DE CONTROL INSTITUCIONAL | I2699: 90 | J2699: REALIZACIÓN DE SERVICIOS DE CONTROL RELACIONADO | K2699: 7 | L2699: 11 | M2699: 38 | N2699: 6361 | O2699: SERVCIO ESPECIALIZADO EN CONTROL GUBERNAMENTAL | P2699: SERVICIO | Q2699: 9000 | R2699: 1 | S2699: 10700772654 | T2699: CUADROS LAGOS IZAMAR ROSALI | U2699: 00 | V2699: =VLOOKUP(U2699,d_ff!A$1:B$5,2,0) -> 00: RECURSOS ORDINARIOS | W2699: 2.3. 2 9. 1 1 | X2699: =VLOOKUP(W2699,d_clasif!B$1:C$1529,2,0) -> 2.3. 2 9. 1 1: LOCACION DE SERVICIOS REALIZADOS POR PERSONAS NATURALES RELACIONADAS AL ROL DE LA ENTIDAD | Y2699: 45 | Z2699: Cadenas Presupuestal: 94=>9001=>3999999=>5000006=>22=>6=>12=>1=>8=>27 Siaf/Ord: 158/58 | AA2699: 2970 | AB2699: 46134
A2700: 2026 | B2700: 333 | C2700: 2 | D2700: S | E2700: 218 | F2700: 172 | G2700: 94.04.04 | H2700: INSTITUTO DE INVESTIGACION | I2700: 378 | J2700: IMPLEMENTACION PARA EL DESARROLLO Y EJECUCION DE LAS ACTIVIDADES PARA LA INVESTIGACION | K2700: 7 | L2700: 11 | M2700: 43 | N2700: 1207 | O2700: SERVICIO DE AUXILIAR ADMINISTRATIVO | P2700: SERVICIO | Q2700: 6000 | R2700: 1 | S2700: 10712403158 | T2700: CONGA CARDENAS JHONY | U2700: 18 | V2700: =VLOOKUP(U2700,d_ff!A$1:B$5,2,0) -> 18: CANON Y SOBRECANON, REGALIAS, RENTA DE ADUANAS Y PARTICIPACIONES | W2700: 2.3. 2 9. 1 1 | X2700: =VLOOKUP(W2700,d_clasif!B$1:C$1529,2,0) -> 2.3. 2 9. 1 1: LOCACION DE SERVICIOS REALIZADOS POR PERSONAS NATURALES RELACIONADAS AL ROL DE LA ENTIDAD | Y2700: 53 | Z2700: Cadenas Presupuestal: 94=>9002=>3999999=>5000894=>22=>48=>15=>1=>334523=>27 Siaf/Ord: 333/172 | AA2700: 1980 | AB2700: 46121
A2701: 2026 | B2701: 334 | C2701: 2 | D2701: S | E2701: 223 | F2701: 173 | G2701: 94.04.04 | H2701: INSTITUTO DE INVESTIGACION | I2701: 378 | J2701: IMPLEMENTACION PARA EL DESARROLLO Y EJECUCION DE LAS ACTIVIDADES PARA LA INVESTIGACION | K2701: 17 | L2701: 1 | M2701: 3 | N2701: 1226 | O2701: SERVICIO DE IMPLEMENTACIÓN DE PLATAFORMA TECNOLÓGICA | P2701: SERVICIO | Q2701: 6000 | R2701: 1 | S2701: 10772239934 | T2701: GUTIERREZ ROJAS ALEXANDRO ANTHONY | U2701: 18 | V2701: =VLOOKUP(U2701,d_ff!A$1:B$5,2,0) -> 18: CANON Y SOBRECANON, REGALIAS, RENTA DE ADUANAS Y PARTICIPACIONES | W2701: 2.3. 2 9. 1 1 | X2701: =VLOOKUP(W2701,d_clasif!B$1:C$1529,2,0) -> 2.3. 2 9. 1 1: LOCACION DE SERVICIOS REALIZADOS POR PERSONAS NATURALES RELACIONADAS AL ROL DE LA ENTIDAD | Y2701: 53 | Z2701: Cadenas Presupuestal: 94=>9002=>3999999=>5000894=>22=>48=>15=>1=>334523=>27 Siaf/Ord: 334/173 | AA2701: 1980 | AB2701: 46120
A2702: 2026 | B2702: 335 | C2702: 2 | D2702: S | E2702: 217 | F2702: 171 | G2702: 94.04.04 | H2702: INSTITUTO DE INVESTIGACION | I2702: 378 | J2702: IMPLEMENTACION PARA EL DESARROLLO Y EJECUCION DE LAS ACTIVIDADES PARA LA INVESTIGACION | K2702: 7 | L2702: 11 | M2702: 44 | N2702: 3759 | O2702: SERVICIO ESPECIALIZADO EN ASISTENCIA TECNICA ADMINISTRATIVA | P2702: SERVICIO | Q2702: 9000 | R2702: 1 | S2702: 10410548807 | T2702: HERRERA TAYPE IRMA MAGALY | U2702: 18 | V2702: =VLOOKUP(U2702,d_ff!A$1:B$5,2,0) -> 18: CANON Y SOBRECANON, REGALIAS, RENTA DE ADUANAS Y PARTICIPACIONES | W2702: 2.3. 2 9. 1 1 | X2702: =VLOOKUP(W2702,d_clasif!B$1:C$1529,2,0) -> 2.3. 2 9. 1 1: LOCACION DE SERVICIOS REALIZADOS POR PERSONAS NATURALES RELACIONADAS AL ROL DE LA ENTIDAD | Y2702: 53 | Z2702: Cadenas Presupuestal: 94=>9002=>3999999=>5000894=>22=>48=>15=>1=>334523=>27 Siaf/Ord: 335/171 | AA2702: 2970 | AB2702: 46120
A2703: 2026 | B2703: 336 | C2703: 2 | D2703: S | E2703: 221 | F2703: 170 | G2703: 94.04.04 | H2703: INSTITUTO DE INVESTIGACION | I2703: 378 | J2703: IMPLEMENTACION PARA EL DESARROLLO Y EJECUCION DE LAS ACTIVIDADES PARA LA INVESTIGACION | K2703: 7 | L2703: 11 | M2703: 44 | N2703: 3759 | O2703: SERVICIO ESPECIALIZADO EN ASISTENCIA TECNICA ADMINISTRATIVA | P2703: SERVICIO | Q2703: 9000 | R2703: 1 | S2703: 10459745284 | T2703: VEGA ROJAS NADIA JOSEFINA | U2703: 18 | V2703: =VLOOKUP(U2703,d_ff!A$1:B$5,2,0) -> 18: CANON Y SOBRECANON, REGALIAS, RENTA DE ADUANAS Y PARTICIPACIONES | W2703: 2.3. 2 9. 1 1 | X2703: =VLOOKUP(W2703,d_clasif!B$1:C$1529,2,0) -> 2.3. 2 9. 1 1: LOCACION DE SERVICIOS REALIZADOS POR PERSONAS NATURALES RELACIONADAS AL ROL DE LA ENTIDAD | Y2703: 53 | Z2703: Cadenas Presupuestal: 94=>9002=>3999999=>5000894=>22=>48=>15=>1=>334523=>27 Siaf/Ord: 336/170 | AA2703: 2970 | AB2703: 46120
A2704: 2026 | B2704: 379 | C2704: 2 | D2704: S | E2704: 220 | F2704: 193 | G2704: 94.04.04 | H2704: INSTITUTO DE INVESTIGACION | I2704: 378 | J2704: IMPLEMENTACION PARA EL DESARROLLO Y EJECUCION DE LAS ACTIVIDADES PARA LA INVESTIGACION | K2704: 70 | L2704: 10 | M2704: 2 | N2704: 151 | O2704: SERVICIO DE DIGITALIZACIÓN DE DOCUMENTOS | P2704: SERVICIO | Q2704: 6000 | R2704: 1 | S2704: 10726069277 | T2704: MENESES NOLASCO THORMAN | U2704: 18 | V2704: =VLOOKUP(U2704,d_ff!A$1:B$5,2,0) -> 18: CANON Y SOBRECANON, REGALIAS, RENTA DE ADUANAS Y PARTICIPACIONES | W2704: 2.3. 2 9. 1 1 | X2704: =VLOOKUP(W2704,d_clasif!B$1:C$1529,2,0) -> 2.3. 2 9. 1 1: LOCACION DE SERVICIOS REALIZADOS POR PERSONAS NATURALES RELACIONADAS AL ROL DE LA ENTIDAD | Y2704: 53 | Z2704: Cadenas Presupuestal: 94=>9002=>3999999=>5000894=>22=>48=>15=>1=>334523=>27 Siaf/Ord: 379/193 | AA2704: 1980 | AB2704: 46132
A2705: 2026 | B2705: 139 | C2705: 2 | D2705: S | E2705: 64 | F2705: 47 | G2705: 94.02.13.06 | H2705: PLANTELES DE APLICACION GUAMAN POMA DE AYALA | I2705: 26 | J2705: IMPLEMENTACIÓN Y DESARROLLO DE LA EDUCACIÓN EN COLEGIOS EXPERIMENTALES | K2705: 87 | L2705: 5 | M2705: 3 | N2705: 19 | O2705: SERVICIO DE INTERNET | P2705: SERVICIO | Q2705: 1200 | R2705: 1 | S2705: 20452245460 | T2705: SOCIEDAD INTEGRADA DE ELECTRONICA Y SISTEMAS SRL | U2705: 00 | V2705: =VLOOKUP(U2705,d_ff!A$1:B$5,2,0) -> 00: RECURSOS ORDINARIOS | W2705: 2.3. 2 2. 2 3 | X2705: =VLOOKUP(W2705,d_clasif!B$1:C$1529,2,0) -> 2.3. 2 2. 2 3: SERVICIO DE INTERNET | Y2705: 47 | Z2705: Cadenas Presupuestal: 94=>9002=>3999999=>5000659=>22=>48=>109=>1=>44444=>1 Siaf/Ord: 139/47 | AA2705: 218.18 | AB2705: 46127
A2706: 2026 | B2706: 417 | C2706: 2 | D2706: S | E2706: 297 | F2706: 220 | G2706: 94.02.13.06 | H2706: PLANTELES DE APLICACION GUAMAN POMA DE AYALA | I2706: 26 | J2706: IMPLEMENTACIÓN Y DESARROLLO DE LA EDUCACIÓN EN COLEGIOS EXPERIMENTALES | K2706: 7 | L2706: 11 | M2706: 44 | N2706: 608 | O2706: SERVICIO DE ASISTENCIA TECNICA Y ORIENTACION EN AUXILIAR EN EDUCACION | P2706: SERVICIO | Q2706: 10000 | R2706: 1 | S2706: 10283163810 | T2706: OCHANTE APAICO ROSA | U2706: 00 | V2706: =VLOOKUP(U2706,d_ff!A$1:B$5,2,0) -> 00: RECURSOS ORDINARIOS | W2706: 2.3. 2 9. 1 1 | X2706: =VLOOKUP(W2706,d_clasif!B$1:C$1529,2,0) -> 2.3. 2 9. 1 1: LOCACION DE SERVICIOS REALIZADOS POR PERSONAS NATURALES RELACIONADAS AL ROL DE LA ENTIDAD | Y2706: 47 | Z2706: Cadenas Presupuestal: 94=>9002=>3999999=>5000659=>22=>48=>109=>1=>44444=>27 Siaf/Ord: 417/220 | AA2706: 2000 | AB2706: 46139
A2707: 2026 | B2707: 418 | C2707: 2 | D2707: S | E2707: 298 | F2707: 221 | G2707: 94.02.13.06 | H2707: PLANTELES DE APLICACION GUAMAN POMA DE AYALA | I2707: 26 | J2707: IMPLEMENTACIÓN Y DESARROLLO DE LA EDUCACIÓN EN COLEGIOS EXPERIMENTALES | K2707: 7 | L2707: 5 | M2707: 4 | N2707: 16 | O2707: SERVICIO ESPECIALIZADO EN PSICOLOGIA | P2707: SERVICIO | Q2707: 10000 | R2707: 1 | S2707: 10739071955 | T2707: GUTIERREZ GAMBOA KELLY ALISSON | U2707: 00 | V2707: =VLOOKUP(U2707,d_ff!A$1:B$5,2,0) -> 00: RECURSOS ORDINARIOS | W2707: 2.3. 2 9. 1 1 | X2707: =VLOOKUP(W2707,d_clasif!B$1:C$1529,2,0) -> 2.3. 2 9. 1 1: LOCACION DE SERVICIOS REALIZADOS POR PERSONAS NATURALES RELACIONADAS AL ROL DE LA ENTIDAD | Y2707: 47 | Z2707: Cadenas Presupuestal: 94=>9002=>3999999=>5000659=>22=>48=>109=>1=>44444=>27 Siaf/Ord: 418/221 | AA2707: 2000 | AB2707: 46137
A2708: 2026 | B2708: 421 | C2708: 2 | D2708: S | E2708: 301 | F2708: 215 | G2708: 94.02.13.06 | H2708: PLANTELES DE APLICACION GUAMAN POMA DE AYALA | I2708: 26 | J2708: IMPLEMENTACIÓN Y DESARROLLO DE LA EDUCACIÓN EN COLEGIOS EXPERIMENTALES | K2708: 7 | L2708: 11 | M2708: 38 | N2708: 898 | O2708: SERVICIOS ESPECIALIZADOS EN EDUCACION PRIMARIA | P2708: SERVICIO | Q2708: 12500 | R2708: 1 | S2708: 10704335682 | T2708: QUISPE PALOMINO TALIA NATALY | U2708: 00 | V2708: =VLOOKUP(U2708,d_ff!A$1:B$5,2,0) -> 00: RECURSOS ORDINARIOS | W2708: 2.3. 2 9. 1 1 | X2708: =VLOOKUP(W2708,d_clasif!B$1:C$1529,2,0) -> 2.3. 2 9. 1 1: LOCACION DE SERVICIOS REALIZADOS POR PERSONAS NATURALES RELACIONADAS AL ROL DE LA ENTIDAD | Y2708: 47 | Z2708: Cadenas Presupuestal: 94=>9002=>3999999=>5000659=>22=>48=>109=>1=>44444=>27 Siaf/Ord: 421/215 | AA2708: 2500 | AB2708: 46139
A2709: 2026 | B2709: 422 | C2709: 2 | D2709: S | E2709: 302 | F2709: 216 | G2709: 94.02.13.06 | H2709: PLANTELES DE APLICACION GUAMAN POMA DE AYALA | I2709: 26 | J2709: IMPLEMENTACIÓN Y DESARROLLO DE LA EDUCACIÓN EN COLEGIOS EXPERIMENTALES | K2709: 25 | L2709: 5 | M2709: 4 | N2709: 150 | O2709: SERVICIO DE ENSEÑANZA DE EDUCACIÓN FÍSICA | P2709: SERVICIO | Q2709: 12500 | R2709: 1 | S2709: 10708956371 | T2709: ACHAHUANCO CUTTI JULIO CESAR | U2709: 00 | V2709: =VLOOKUP(U2709,d_ff!A$1:B$5,2,0) -> 00: RECURSOS ORDINARIOS | W2709: 2.3. 2 9. 1 1 | X2709: =VLOOKUP(W2709,d_clasif!B$1:C$1529,2,0) -> 2.3. 2 9. 1 1: LOCACION DE SERVICIOS REALIZADOS POR PERSONAS NATURALES RELACIONADAS AL ROL DE LA ENTIDAD | Y2709: 47 | Z2709: Cadenas Presupuestal: 94=>9002=>3999999=>5000659=>22=>48=>109=>1=>44444=>27 Siaf/Ord: 422/216 | AA2709: 2500 | AB2709: 46126
A2710: 2026 | B2710: 423 | C2710: 2 | D2710: S | E2710: 295 | F2710: 219 | G2710: 94.02.13.06 | H2710: PLANTELES DE APLICACION GUAMAN POMA DE AYALA | I2710: 26 | J2710: IMPLEMENTACIÓN Y DESARROLLO DE LA EDUCACIÓN EN COLEGIOS EXPERIMENTALES | K2710: 25 | L2710: 5 | M2710: 4 | N2710: 150 | O2710: SERVICIO DE ENSEÑANZA DE EDUCACIÓN FÍSICA | P2710: SERVICIO | Q2710: 12500 | R2710: 1 | S2710: 10743476609 | T2710: YARANGA OJEDA EDITH ANDREHINA | U2710: 00 | V2710: =VLOOKUP(U2710,d_ff!A$1:B$5,2,0) -> 00: RECURSOS ORDINARIOS | W2710: 2.3. 2 9. 1 1 | X2710: =VLOOKUP(W2710,d_clasif!B$1:C$1529,2,0) -> 2.3. 2 9. 1 1: LOCACION DE SERVICIOS REALIZADOS POR PERSONAS NATURALES RELACIONADAS AL ROL DE LA ENTIDAD | Y2710: 47 | Z2710: Cadenas Presupuestal: 94=>9002=>3999999=>5000659=>22=>48=>109=>1=>44444=>27 Siaf/Ord: 423/219 | AA2710: 2500 | AB2710: 46136
A2711: 2026 | B2711: 495 | C2711: 2 | D2711: S | E2711: 348 | F2711: 245 | G2711: 94.02.13.06 | H2711: PLANTELES DE APLICACION GUAMAN POMA DE AYALA | I2711: 26 | J2711: IMPLEMENTACIÓN Y DESARROLLO DE LA EDUCACIÓN EN COLEGIOS EXPERIMENTALES | K2711: 7 | L2711: 5 | M2711: 4 | N2711: 14 | O2711: SERVICIO ESPECIALIZADO EN EDUCACION | P2711: SERVICIO | Q2711: 7500 | R2711: 1 | S2711: 10283054956 | T2711: GOMEZ CARRASCO PETER RIGOBERTO | U2711: 00 | V2711: =VLOOKUP(U2711,d_ff!A$1:B$5,2,0) -> 00: RECURSOS ORDINARIOS | W2711: 2.3. 2 9. 1 1 | X2711: =VLOOKUP(W2711,d_clasif!B$1:C$1529,2,0) -> 2.3. 2 9. 1 1: LOCACION DE SERVICIOS REALIZADOS POR PERSONAS NATURALES RELACIONADAS AL ROL DE LA ENTIDAD | Y2711: 47 | Z2711: Cadenas Presupuestal: 94=>9002=>3999999=>5000659=>22=>48=>109=>1=>44444=>27 Siaf/Ord: 495/245 | AA2711: 2500 | AB2711: 46134
... A2925: 2026 | B2925: 165 | C2925: 2 | D2925: S | E2925: 86 | F2925: 70 | G2925: 94.02.02 | H2925: OFICINA DE ASESORIA JURIDICA | I2925: 252 | J2925: ATENCIÓN DE ACCIONES DE DEFENSA LEGAL DE LOS INTERESES INSTITUCIONALES EN PROCESOS JUDICIALES | K2925: 7 | L2925: 5 | M2925: 4 | N2925: 43 | O2925: SERVICIO ESPECIALIZADO EN MATERIA LEGAL | P2925: SERVICIO | Q2925: 10500 | R2925: 1 | S2925: 10436811123 | T2925: BOCANGEL MAMANI HANS ENDELBERTH | U2925: 00 | V2925: =VLOOKUP(U2925,d_ff!A$1:B$5,2,0) -> 00: RECURSOS ORDINARIOS | W2925: 2.3. 2 9. 1 1 | X2925: =VLOOKUP(W2925,d_clasif!B$1:C$1529,2,0) -> 2.3. 2 9. 1 1: LOCACION DE SERVICIOS REALIZADOS POR PERSONAS NATURALES RELACIONADAS AL ROL DE LA ENTIDAD | Y2925: 43 | Z2925: Cadenas Presupuestal: 94=>9001=>3999999=>5000004=>22=>6=>8=>1=>12=>27 Siaf/Ord: 165/70 | AA2925: 3570 | AB2925: 46154
A2926: 2026 | B2926: 158 | C2926: 2 | D2926: S | E2926: 89 | F2926: 58 | G2926: 94.01 | H2926: ORGANO DE CONTROL INSTITUCIONAL | I2926: 90 | J2926: REALIZACIÓN DE SERVICIOS DE CONTROL RELACIONADO | K2926: 7 | L2926: 11 | M2926: 38 | N2926: 6361 | O2926: SERVCIO ESPECIALIZADO EN CONTROL GUBERNAMENTAL | P2926: SERVICIO | Q2926: 9000 | R2926: 1 | S2926: 10700772654 | T2926: CUADROS LAGOS IZAMAR ROSALI | U2926: 00 | V2926: =VLOOKUP(U2926,d_ff!A$1:B$5,2,0) -> 00: RECURSOS ORDINARIOS | W2926: 2.3. 2 9. 1 1 | X2926: =VLOOKUP(W2926,d_clasif!B$1:C$1529,2,0) -> 2.3. 2 9. 1 1: LOCACION DE SERVICIOS REALIZADOS POR PERSONAS NATURALES RELACIONADAS AL ROL DE LA ENTIDAD | Y2926: 45 | Z2926: Cadenas Presupuestal: 94=>9001=>3999999=>5000006=>22=>6=>12=>1=>8=>27 Siaf/Ord: 158/58 | AA2926: 3060 | AB2926: 46157
A2927: 2026 | B2927: 333 | C2927: 2 | D2927: S | E2927: 218 | F2927: 172 | G2927: 94.04.04 | H2927: INSTITUTO DE INVESTIGACION | I2927: 378 | J2927: IMPLEMENTACION PARA EL DESARROLLO Y EJECUCION DE LAS ACTIVIDADES PARA LA INVESTIGACION | K2927: 7 | L2927: 11 | M2927: 43 | N2927: 1207 | O2927: SERVICIO DE AUXILIAR ADMINISTRATIVO | P2927: SERVICIO | Q2927: 6000 | R2927: 1 | S2927: 10712403158 | T2927: CONGA CARDENAS JHONY | U2927: 18 | V2927: =VLOOKUP(U2927,d_ff!A$1:B$5,2,0) -> 18: CANON Y SOBRECANON, REGALIAS, RENTA DE ADUANAS Y PARTICIPACIONES | W2927: 2.3. 2 9. 1 1 | X2927: =VLOOKUP(W2927,d_clasif!B$1:C$1529,2,0) -> 2.3. 2 9. 1 1: LOCACION DE SERVICIOS REALIZADOS POR PERSONAS NATURALES RELACIONADAS AL ROL DE LA ENTIDAD | Y2927: 53 | Z2927: Cadenas Presupuestal: 94=>9002=>3999999=>5000894=>22=>48=>15=>1=>334523=>27 Siaf/Ord: 333/172 | AA2927: 1980 | AB2927: 46148
A2928: 2026 | B2928: 334 | C2928: 2 | D2928: S | E2928: 223 | F2928: 173 | G2928: 94.04.04 | H2928: INSTITUTO DE INVESTIGACION | I2928: 378 | J2928: IMPLEMENTACION PARA EL DESARROLLO Y EJECUCION DE LAS ACTIVIDADES PARA LA INVESTIGACION | K2928: 17 | L2928: 1 | M2928: 3 | N2928: 1226 | O2928: SERVICIO DE IMPLEMENTACIÓN DE PLATAFORMA TECNOLÓGICA | P2928: SERVICIO | Q2928: 6000 | R2928: 1 | S2928: 10772239934 | T2928: GUTIERREZ ROJAS ALEXANDRO ANTHONY | U2928: 18 | V2928: =VLOOKUP(U2928,d_ff!A$1:B$5,2,0) -> 18: CANON Y SOBRECANON, REGALIAS, RENTA DE ADUANAS Y PARTICIPACIONES | W2928: 2.3. 2 9. 1 1 | X2928: =VLOOKUP(W2928,d_clasif!B$1:C$1529,2,0) -> 2.3. 2 9. 1 1: LOCACION DE SERVICIOS REALIZADOS POR PERSONAS NATURALES RELACIONADAS AL ROL DE LA ENTIDAD | Y2928: 53 | Z2928: Cadenas Presupuestal: 94=>9002=>3999999=>5000894=>22=>48=>15=>1=>334523=>27 Siaf/Ord: 334/173 | AA2928: 1980 | AB2928: 46148
A2929: 2026 | B2929: 335 | C2929: 2 | D2929: S | E2929: 217 | F2929: 171 | G2929: 94.04.04 | H2929: INSTITUTO DE INVESTIGACION | I2929: 378 | J2929: IMPLEMENTACION PARA EL DESARROLLO Y EJECUCION DE LAS ACTIVIDADES PARA LA INVESTIGACION | K2929: 7 | L2929: 11 | M2929: 44 | N2929: 3759 | O2929: SERVICIO ESPECIALIZADO EN ASISTENCIA TECNICA ADMINISTRATIVA | P2929: SERVICIO | Q2929: 9000 | R2929: 1 | S2929: 10410548807 | T2929: HERRERA TAYPE IRMA MAGALY | U2929: 18 | V2929: =VLOOKUP(U2929,d_ff!A$1:B$5,2,0) -> 18: CANON Y SOBRECANON, REGALIAS, RENTA DE ADUANAS Y PARTICIPACIONES | W2929: 2.3. 2 9. 1 1 | X2929: =VLOOKUP(W2929,d_clasif!B$1:C$1529,2,0) -> 2.3. 2 9. 1 1: LOCACION DE SERVICIOS REALIZADOS POR PERSONAS NATURALES RELACIONADAS AL ROL DE LA ENTIDAD | Y2929: 53 | Z2929: Cadenas Presupuestal: 94=>9002=>3999999=>5000894=>22=>48=>15=>1=>334523=>27 Siaf/Ord: 335/171 | AA2929: 2970 | AB2929: 46148
A2930: 2026 | B2930: 336 | C2930: 2 | D2930: S | E2930: 221 | F2930: 170 | G2930: 94.04.04 | H2930: INSTITUTO DE INVESTIGACION | I2930: 378 | J2930: IMPLEMENTACION PARA EL DESARROLLO Y EJECUCION DE LAS ACTIVIDADES PARA LA INVESTIGACION | K2930: 7 | L2930: 11 | M2930: 44 | N2930: 3759 | O2930: SERVICIO ESPECIALIZADO EN ASISTENCIA TECNICA ADMINISTRATIVA | P2930: SERVICIO | Q2930: 9000 | R2930: 1 | S2930: 10459745284 | T2930: VEGA ROJAS NADIA JOSEFINA | U2930: 18 | V2930: =VLOOKUP(U2930,d_ff!A$1:B$5,2,0) -> 18: CANON Y SOBRECANON, REGALIAS, RENTA DE ADUANAS Y PARTICIPACIONES | W2930: 2.3. 2 9. 1 1 | X2930: =VLOOKUP(W2930,d_clasif!B$1:C$1529,2,0) -> 2.3. 2 9. 1 1: LOCACION DE SERVICIOS REALIZADOS POR PERSONAS NATURALES RELACIONADAS AL ROL DE LA ENTIDAD | Y2930: 53 | Z2930: Cadenas Presupuestal: 94=>9002=>3999999=>5000894=>22=>48=>15=>1=>334523=>27 Siaf/Ord: 336/170 | AA2930: 2970 | AB2930: 46148
A2931: 2026 | B2931: 379 | C2931: 2 | D2931: S | E2931: 220 | F2931: 193 | G2931: 94.04.04 | H2931: INSTITUTO DE INVESTIGACION | I2931: 378 | J2931: IMPLEMENTACION PARA EL DESARROLLO Y EJECUCION DE LAS ACTIVIDADES PARA LA INVESTIGACION | K2931: 70 | L2931: 10 | M2931: 2 | N2931: 151 | O2931: SERVICIO DE DIGITALIZACIÓN DE DOCUMENTOS | P2931: SERVICIO | Q2931: 6000 | R2931: 1 | S2931: 10726069277 | T2931: MENESES NOLASCO THORMAN | U2931: 18 | V2931: =VLOOKUP(U2931,d_ff!A$1:B$5,2,0) -> 18: CANON Y SOBRECANON, REGALIAS, RENTA DE ADUANAS Y PARTICIPACIONES | W2931: 2.3. 2 9. 1 1 | X2931: =VLOOKUP(W2931,d_clasif!B$1:C$1529,2,0) -> 2.3. 2 9. 1 1: LOCACION DE SERVICIOS REALIZADOS POR PERSONAS NATURALES RELACIONADAS AL ROL DE LA ENTIDAD | Y2931: 53 | Z2931: Cadenas Presupuestal: 94=>9002=>3999999=>5000894=>22=>48=>15=>1=>334523=>27 Siaf/Ord: 379/193 | AA2931: 1980 | AB2931: 46155
A2932: 2026 | B2932: 415 | C2932: 2 | D2932: S | E2932: 303 | F2932: 217 | G2932: 94.02.13.06 | H2932: PLANTELES DE APLICACION GUAMAN POMA DE AYALA | I2932: 26 | J2932: IMPLEMENTACIÓN Y DESARROLLO DE LA EDUCACIÓN EN COLEGIOS EXPERIMENTALES | K2932: 7 | L2932: 5 | M2932: 4 | N2932: 14 | O2932: SERVICIO ESPECIALIZADO EN EDUCACION | P2932: SERVICIO | Q2932: 6250 | R2932: 1 | S2932: 10282602241 | T2932: LOAYZA FLORES DANIEL GUIDO | U2932: 00 | V2932: =VLOOKUP(U2932,d_ff!A$1:B$5,2,0) -> 00: RECURSOS ORDINARIOS | W2932: 2.3. 2 9. 1 1 | X2932: =VLOOKUP(W2932,d_clasif!B$1:C$1529,2,0) -> 2.3. 2 9. 1 1: LOCACION DE SERVICIOS REALIZADOS POR PERSONAS NATURALES RELACIONADAS AL ROL DE LA ENTIDAD | Y2932: 47 | Z2932: Cadenas Presupuestal: 94=>9002=>3999999=>5000659=>22=>48=>109=>1=>44444=>27 Siaf/Ord: 415/217 | AA2932: 1250 | AB2932: 46171
A2933: 2026 | B2933: 415 | C2933: 2 | D2933: S | E2933: 303 | F2933: 217 | G2933: 94.02.13.06 | H2933: PLANTELES DE APLICACION GUAMAN POMA DE AYALA | I2933: 26 | J2933: IMPLEMENTACIÓN Y DESARROLLO DE LA EDUCACIÓN EN COLEGIOS EXPERIMENTALES | K2933: 7 | L2933: 5 | M2933: 4 | N2933: 14 | O2933: SERVICIO ESPECIALIZADO EN EDUCACION | P2933: SERVICIO | Q2933: 6250 | R2933: 1 | S2933: 10282602241 | T2933: LOAYZA FLORES DANIEL GUIDO | U2933: 00 | V2933: =VLOOKUP(U2933,d_ff!A$1:B$5,2,0) -> 00: RECURSOS ORDINARIOS | W2933: 2.3. 2 9. 1 1 | X2933: =VLOOKUP(W2933,d_clasif!B$1:C$1529,2,0) -> 2.3. 2 9. 1 1: LOCACION DE SERVICIOS REALIZADOS POR PERSONAS NATURALES RELACIONADAS AL ROL DE LA ENTIDAD | Y2933: 47 | Z2933: Cadenas Presupuestal: 94=>9002=>3999999=>5000659=>22=>48=>109=>1=>44444=>27 Siaf/Ord: 415/217 | AA2933: 1250 | AB2933: 46171
A2934: 2026 | B2934: 416 | C2934: 2 | D2934: S | E2934: 296 | F2934: 218 | G2934: 94.02.13.06 | H2934: PLANTELES DE APLICACION GUAMAN POMA DE AYALA | I2934: 26 | J2934: IMPLEMENTACIÓN Y DESARROLLO DE LA EDUCACIÓN EN COLEGIOS EXPERIMENTALES | K2934: 7 | L2934: 11 | M2934: 38 | N2934: 899 | O2934: SERVICIOS ESPECIALIZADOS EN EDUCACION SECUNDARIA | P2934: SERVICIO | Q2934: 12500 | R2934: 1 | S2934: 10282732616 | T2934: BUITRON BERROCAL TULIO RAMIRO | U2934: 00 | V2934: =VLOOKUP(U2934,d_ff!A$1:B$5,2,0) -> 00: RECURSOS ORDINARIOS | W2934: 2.3. 2 9. 1 1 | X2934: =VLOOKUP(W2934,d_clasif!B$1:C$1529,2,0) -> 2.3. 2 9. 1 1: LOCACION DE SERVICIOS REALIZADOS POR PERSONAS NATURALES RELACIONADAS AL ROL DE LA ENTIDAD | Y2934: 47 | Z2934: Cadenas Presupuestal: 94=>9002=>3999999=>5000659=>22=>48=>109=>1=>44444=>27 Siaf/Ord: 416/218 | AA2934: 2500 | AB2934: 46171
A2935: 2026 | B2935: 417 | C2935: 2 | D2935: S | E2935: 297 | F2935: 220 | G2935: 94.02.13.06 | H2935: PLANTELES DE APLICACION GUAMAN POMA DE AYALA | I2935: 26 | J2935: IMPLEMENTACIÓN Y DESARROLLO DE LA EDUCACIÓN EN COLEGIOS EXPERIMENTALES | K2935: 7 | L2935: 11 | M2935: 44 | N2935: 608 | O2935: SERVICIO DE ASISTENCIA TECNICA Y ORIENTACION EN AUXILIAR EN EDUCACION | P2935: SERVICIO | Q2935: 10000 | R2935: 1 | S2935: 10283163810 | T2935: OCHANTE APAICO ROSA | U2935: 00 | V2935: =VLOOKUP(U2935,d_ff!A$1:B$5,2,0) -> 00: RECURSOS ORDINARIOS | W2935: 2.3. 2 9. 1 1 | X2935: =VLOOKUP(W2935,d_clasif!B$1:C$1529,2,0) -> 2.3. 2 9. 1 1: LOCACION DE SERVICIOS REALIZADOS POR PERSONAS NATURALES RELACIONADAS AL ROL DE LA ENTIDAD | Y2935: 47 | Z2935: Cadenas Presupuestal: 94=>9002=>3999999=>5000659=>22=>48=>109=>1=>44444=>27 Siaf/Ord: 417/220 | AA2935: 2000 | AB2935: 46167
A2936: 2026 | B2936: 418 | C2936: 2 | D2936: S | E2936: 298 | F2936: 221 | G2936: 94.02.13.06 | H2936: PLANTELES DE APLICACION GUAMAN POMA DE AYALA | I2936: 26 | J2936: IMPLEMENTACIÓN Y DESARROLLO DE LA EDUCACIÓN EN COLEGIOS EXPERIMENTALES | K2936: 7 | L2936: 5 | M2936: 4 | N2936: 16 | O2936: SERVICIO ESPECIALIZADO EN PSICOLOGIA | P2936: SERVICIO | Q2936: 10000 | R2936: 1 | S2936: 10739071955 | T2936: GUTIERREZ GAMBOA KELLY ALISSON | U2936: 00 | V2936: =VLOOKUP(U2936,d_ff!A$1:B$5,2,0) -> 00: RECURSOS ORDINARIOS | W2936: 2.3. 2 9. 1 1 | X2936: =VLOOKUP(W2936,d_clasif!B$1:C$1529,2,0) -> 2.3. 2 9. 1 1: LOCACION DE SERVICIOS REALIZADOS POR PERSONAS NATURALES RELACIONADAS AL ROL DE LA ENTIDAD | Y2936: 47 | Z2936: Cadenas Presupuestal: 94=>9002=>3999999=>5000659=>22=>48=>109=>1=>44444=>27 Siaf/Ord: 418/221 | AA2936: 2000 | AB2936: 46167
A2937: 2026 | B2937: 419 | C2937: 2 | D2937: S | E2937: 299 | F2937: 222 | G2937: 94.02.13.06 | H2937: PLANTELES DE APLICACION GUAMAN POMA DE AYALA | I2937: 26 | J2937: IMPLEMENTACIÓN Y DESARROLLO DE LA EDUCACIÓN EN COLEGIOS EXPERIMENTALES | K2937: 7 | L2937: 11 | M2937: 38 | N2937: 3521 | O2937: SERVICIO ESPECIALIZADO EN TRABAJO SOCIAL | P2937: SERVICIO | Q2937: 10000 | R2937: 1 | S2937: 10752853792 | T2937: RIVEROS LIZANA BRIYET | U2937: 00 | V2937: =VLOOKUP(U2937,d_ff!A$1:B$5,2,0) -> 00: RECURSOS ORDINARIOS | W2937: 2.3. 2 9. 1 1 | X2937: =VLOOKUP(W2937,d_clasif!B$1:C$1529,2,0) -> 2.3. 2 9. 1 1: LOCACION DE SERVICIOS REALIZADOS POR PERSONAS NATURALES RELACIONADAS AL ROL DE LA ENTIDAD | Y2937: 47 | Z2937: Cadenas Presupuestal: 94=>9002=>3999999=>5000659=>22=>48=>109=>1=>44444=>27 Siaf/Ord: 419/222 | AA2937: 2000 | AB2937: 46171
A2938: 2026 | B2938: 420 | C2938: 2 | D2938: S | E2938: 300 | F2938: 214 | G2938: 94.02.13.06 | H2938: PLANTELES DE APLICACION GUAMAN POMA DE AYALA | I2938: 26 | J2938: IMPLEMENTACIÓN Y DESARROLLO DE LA EDUCACIÓN EN COLEGIOS EXPERIMENTALES | K2938: 7 | L2938: 11 | M2938: 38 | N2938: 898 | O2938: SERVICIOS ESPECIALIZADOS EN EDUCACION PRIMARIA | P2938: SERVICIO | Q2938: 12500 | R2938: 1 | S2938: 10704744426 | T2938: BEJAR YUPANQUI YENI YUDITH | U2938: 00 | V2938: =VLOOKUP(U2938,d_ff!A$1:B$5,2,0) -> 00: RECURSOS ORDINARIOS | W2938: 2.3. 2 9. 1 1 | X2938: =VLOOKUP(W2938,d_clasif!B$1:C$1529,2,0) -> 2.3. 2 9. 1 1: LOCACION DE SERVICIOS REALIZADOS POR PERSONAS NATURALES RELACIONADAS AL ROL DE LA ENTIDAD | Y2938: 47 | Z2938: Cadenas Presupuestal: 94=>9002=>3999999=>5000659=>22=>48=>109=>1=>44444=>27 Siaf/Ord: 420/214 | AA2938: 2500 | AB2938: 46171
... A3250: 2026 | B3250: 1295 | C3250: 2 | D3250: S | E3250: 952 | F3250: 646 | G3250: 94.02.02 | H3250: OFICINA DE ASESORIA JURIDICA | I3250: 252 | J3250: ATENCIÓN DE ACCIONES DE DEFENSA LEGAL DE LOS INTERESES INSTITUCIONALES EN PROCESOS JUDICIALES | K3250: 7 | L3250: 1 | M3250: 25 | N3250: 18 | O3250: ASESORIA LEGAL | P3250: SERVICIO | Q3250: 10500 | R3250: 1 | S3250: 10724721082 | T3250: GUTIERREZ CACERES ARACELI FATIMA | U3250: 00 | V3250: =VLOOKUP(U3250,d_ff!A$1:B$5,2,0) -> 00: RECURSOS ORDINARIOS | W3250: 2.3. 2 9. 1 1 | X3250: =VLOOKUP(W3250,d_clasif!B$1:C$1529,2,0) -> 2.3. 2 9. 1 1: LOCACION DE SERVICIOS REALIZADOS POR PERSONAS NATURALES RELACIONADAS AL ROL DE LA ENTIDAD | Y3250: 43 | Z3250: Cadenas Presupuestal: 94=>9001=>3999999=>5000004=>22=>6=>8=>1=>12=>27 Siaf/Ord: 1295/646 | AA3250: 3465 | AB3250: 46186
A3251: 2026 | B3251: 1299 | C3251: 2 | D3251: S | E3251: 953 | F3251: 633 | G3251: 94.01 | H3251: ORGANO DE CONTROL INSTITUCIONAL | I3251: 90 | J3251: REALIZACIÓN DE SERVICIOS DE CONTROL RELACIONADO | K3251: 7 | L3251: 11 | M3251: 38 | N3251: 6361 | O3251: SERVCIO ESPECIALIZADO EN CONTROL GUBERNAMENTAL | P3251: SERVICIO | Q3251: 9000 | R3251: 1 | S3251: 10700772654 | T3251: CUADROS LAGOS IZAMAR ROSALI | U3251: 00 | V3251: =VLOOKUP(U3251,d_ff!A$1:B$5,2,0) -> 00: RECURSOS ORDINARIOS | W3251: 2.3. 2 9. 1 1 | X3251: =VLOOKUP(W3251,d_clasif!B$1:C$1529,2,0) -> 2.3. 2 9. 1 1: LOCACION DE SERVICIOS REALIZADOS POR PERSONAS NATURALES RELACIONADAS AL ROL DE LA ENTIDAD | Y3251: 45 | Z3251: Cadenas Presupuestal: 94=>9001=>3999999=>5000006=>22=>6=>12=>1=>8=>27 Siaf/Ord: 1299/633 | AA3251: 2970 | AB3251: 46190
A3252: 2026 | B3252: 1058 | C3252: 2 | D3252: S | E3252: 779 | F3252: 481 | G3252: 94.02.08.07 | H3252: UNIDAD EJECUTORA DE INVERSIONES | I3252: 403 | J3252: MANTENIMIENTO DE LOS AMBIENTES DEL PABELLON N DE LA ESCUELA DE INGENIERIA CIVIL DE LA UNSCH | K3252: 7 | L3252: 11 | M3252: 38 | N3252: 770 | O3252: SERVICIO DE ASISTENCIA TECNICA EN INGENIERIA | P3252: SERVICIO | Q3252: 4000 | R3252: 1 | S3252: 10471492448 | T3252: PEREZ CONTRERAS JHONATHAN CRISTHIAN | U3252: 13 | V3252: =VLOOKUP(U3252,d_ff!A$1:B$5,2,0) -> 13: DONACIONES Y TRANSFERENCIAS | W3252: 2.3. 2 7.14 98 | X3252: =VLOOKUP(W3252,d_clasif!B$1:C$1529,2,0) -> 2.3. 2 7.14 98: OTROS SERVICIOS TECNICOS Y PROFESIONALES DESARROLLADOS POR PERSONAS NATURALES | Y3252: 81 | Z3252: Cadenas Presupuestal: 94=>9002=>3999999=>5000993=>22=>9=>109=>1=>1119=>27 Siaf/Ord: 1058/481 | AA3252: 4000 | AB3252: 46183
A3253: 2026 | B3253: 1208 | C3253: 2 | D3253: S | E3253: 826 | F3253: 551 | G3253: 94.04.04 | H3253: INSTITUTO DE INVESTIGACION | I3253: 407 | J3253: PROPIEDAD HIPOGLICEMIANTE ANTIINFLAMATORIA Y HEPATOPROTECTOR DE LAS SAPONINAS EXTRAIDAS DE LAS SEMILLAS DE CHENOPODIUM QUINOA WILLD QUINUA | K3253: 7 | L3253: 11 | M3253: 38 | N3253: 3423 | O3253: SERVICIO DE ASISTENCIA EN TEMAS DE INVESTIGACION | P3253: SERVICIO | Q3253: 6600 | R3253: 1 | S3253: 10700912545 | T3253: CURI MEJIA CANDY EMILY | U3253: 18 | V3253: =VLOOKUP(U3253,d_ff!A$1:B$5,2,0) -> 18: CANON Y SOBRECANON, REGALIAS, RENTA DE ADUANAS Y PARTICIPACIONES | W3253: 2.3. 2 7.14 98 | X3253: =VLOOKUP(W3253,d_clasif!B$1:C$1529,2,0) -> 2.3. 2 7.14 98: OTROS SERVICIOS TECNICOS Y PROFESIONALES DESARROLLADOS POR PERSONAS NATURALES | Y3253: 53 | Z3253: Cadenas Presupuestal: 94=>9002=>3999999=>5000894=>22=>48=>15=>1=>334523=>27 Siaf/Ord: 1208/551 | AA3253: 1122 | AB3253: 46195
A3254: 2026 | B3254: 333 | C3254: 2 | D3254: S | E3254: 218 | F3254: 172 | G3254: 94.04.04 | H3254: INSTITUTO DE INVESTIGACION | I3254: 378 | J3254: IMPLEMENTACION PARA EL DESARROLLO Y EJECUCION DE LAS ACTIVIDADES PARA LA INVESTIGACION | K3254: 7 | L3254: 11 | M3254: 43 | N3254: 1207 | O3254: SERVICIO DE AUXILIAR ADMINISTRATIVO | P3254: SERVICIO | Q3254: 6000 | R3254: 1 | S3254: 10712403158 | T3254: CONGA CARDENAS JHONY | U3254: 18 | V3254: =VLOOKUP(U3254,d_ff!A$1:B$5,2,0) -> 18: CANON Y SOBRECANON, REGALIAS, RENTA DE ADUANAS Y PARTICIPACIONES | W3254: 2.3. 2 9. 1 1 | X3254: =VLOOKUP(W3254,d_clasif!B$1:C$1529,2,0) -> 2.3. 2 9. 1 1: LOCACION DE SERVICIOS REALIZADOS POR PERSONAS NATURALES RELACIONADAS AL ROL DE LA ENTIDAD | Y3254: 53 | Z3254: Cadenas Presupuestal: 94=>9002=>3999999=>5000894=>22=>48=>15=>1=>334523=>27 Siaf/Ord: 333/172 | AA3254: 2040 | AB3254: 46176
A3255: 2026 | B3255: 334 | C3255: 2 | D3255: S | E3255: 223 | F3255: 173 | G3255: 94.04.04 | H3255: INSTITUTO DE INVESTIGACION | I3255: 378 | J3255: IMPLEMENTACION PARA EL DESARROLLO Y EJECUCION DE LAS ACTIVIDADES PARA LA INVESTIGACION | K3255: 17 | L3255: 1 | M3255: 3 | N3255: 1226 | O3255: SERVICIO DE IMPLEMENTACIÓN DE PLATAFORMA TECNOLÓGICA | P3255: SERVICIO | Q3255: 6000 | R3255: 1 | S3255: 10772239934 | T3255: GUTIERREZ ROJAS ALEXANDRO ANTHONY | U3255: 18 | V3255: =VLOOKUP(U3255,d_ff!A$1:B$5,2,0) -> 18: CANON Y SOBRECANON, REGALIAS, RENTA DE ADUANAS Y PARTICIPACIONES | W3255: 2.3. 2 9. 1 1 | X3255: =VLOOKUP(W3255,d_clasif!B$1:C$1529,2,0) -> 2.3. 2 9. 1 1: LOCACION DE SERVICIOS REALIZADOS POR PERSONAS NATURALES RELACIONADAS AL ROL DE LA ENTIDAD | Y3255: 53 | Z3255: Cadenas Presupuestal: 94=>9002=>3999999=>5000894=>22=>48=>15=>1=>334523=>27 Siaf/Ord: 334/173 | AA3255: 2040 | AB3255: 46176
A3256: 2026 | B3256: 335 | C3256: 2 | D3256: S | E3256: 217 | F3256: 171 | G3256: 94.04.04 | H3256: INSTITUTO DE INVESTIGACION | I3256: 378 | J3256: IMPLEMENTACION PARA EL DESARROLLO Y EJECUCION DE LAS ACTIVIDADES PARA LA INVESTIGACION | K3256: 7 | L3256: 11 | M3256: 44 | N3256: 3759 | O3256: SERVICIO ESPECIALIZADO EN ASISTENCIA TECNICA ADMINISTRATIVA | P3256: SERVICIO | Q3256: 9000 | R3256: 1 | S3256: 10410548807 | T3256: HERRERA TAYPE IRMA MAGALY | U3256: 18 | V3256: =VLOOKUP(U3256,d_ff!A$1:B$5,2,0) -> 18: CANON Y SOBRECANON, REGALIAS, RENTA DE ADUANAS Y PARTICIPACIONES | W3256: 2.3. 2 9. 1 1 | X3256: =VLOOKUP(W3256,d_clasif!B$1:C$1529,2,0) -> 2.3. 2 9. 1 1: LOCACION DE SERVICIOS REALIZADOS POR PERSONAS NATURALES RELACIONADAS AL ROL DE LA ENTIDAD | Y3256: 53 | Z3256: Cadenas Presupuestal: 94=>9002=>3999999=>5000894=>22=>48=>15=>1=>334523=>27 Siaf/Ord: 335/171 | AA3256: 3060 | AB3256: 46176
A3257: 2026 | B3257: 336 | C3257: 2 | D3257: S | E3257: 221 | F3257: 170 | G3257: 94.04.04 | H3257: INSTITUTO DE INVESTIGACION | I3257: 378 | J3257: IMPLEMENTACION PARA EL DESARROLLO Y EJECUCION DE LAS ACTIVIDADES PARA LA INVESTIGACION | K3257: 7 | L3257: 11 | M3257: 44 | N3257: 3759 | O3257: SERVICIO ESPECIALIZADO EN ASISTENCIA TECNICA ADMINISTRATIVA | P3257: SERVICIO | Q3257: 9000 | R3257: 1 | S3257: 10459745284 | T3257: VEGA ROJAS NADIA JOSEFINA | U3257: 18 | V3257: =VLOOKUP(U3257,d_ff!A$1:B$5,2,0) -> 18: CANON Y SOBRECANON, REGALIAS, RENTA DE ADUANAS Y PARTICIPACIONES | W3257: 2.3. 2 9. 1 1 | X3257: =VLOOKUP(W3257,d_clasif!B$1:C$1529,2,0) -> 2.3. 2 9. 1 1: LOCACION DE SERVICIOS REALIZADOS POR PERSONAS NATURALES RELACIONADAS AL ROL DE LA ENTIDAD | Y3257: 53 | Z3257: Cadenas Presupuestal: 94=>9002=>3999999=>5000894=>22=>48=>15=>1=>334523=>27 Siaf/Ord: 336/170 | AA3257: 3060 | AB3257: 46176
A3258: 2026 | B3258: 379 | C3258: 2 | D3258: S | E3258: 220 | F3258: 193 | G3258: 94.04.04 | H3258: INSTITUTO DE INVESTIGACION | I3258: 378 | J3258: IMPLEMENTACION PARA EL DESARROLLO Y EJECUCION DE LAS ACTIVIDADES PARA LA INVESTIGACION | K3258: 70 | L3258: 10 | M3258: 2 | N3258: 151 | O3258: SERVICIO DE DIGITALIZACIÓN DE DOCUMENTOS | P3258: SERVICIO | Q3258: 6000 | R3258: 1 | S3258: 10726069277 | T3258: MENESES NOLASCO THORMAN | U3258: 18 | V3258: =VLOOKUP(U3258,d_ff!A$1:B$5,2,0) -> 18: CANON Y SOBRECANON, REGALIAS, RENTA DE ADUANAS Y PARTICIPACIONES | W3258: 2.3. 2 9. 1 1 | X3258: =VLOOKUP(W3258,d_clasif!B$1:C$1529,2,0) -> 2.3. 2 9. 1 1: LOCACION DE SERVICIOS REALIZADOS POR PERSONAS NATURALES RELACIONADAS AL ROL DE LA ENTIDAD | Y3258: 53 | Z3258: Cadenas Presupuestal: 94=>9002=>3999999=>5000894=>22=>48=>15=>1=>334523=>27 Siaf/Ord: 379/193 | AA3258: 2040 | AB3258: 46182
A3259: 2026 | B3259: 415 | C3259: 2 | D3259: S | E3259: 303 | F3259: 217 | G3259: 94.02.13.06 | H3259: PLANTELES DE APLICACION GUAMAN POMA DE AYALA | I3259: 26 | J3259: IMPLEMENTACIÓN Y DESARROLLO DE LA EDUCACIÓN EN COLEGIOS EXPERIMENTALES | K3259: 7 | L3259: 5 | M3259: 4 | N3259: 14 | O3259: SERVICIO ESPECIALIZADO EN EDUCACION | P3259: SERVICIO | Q3259: 6250 | R3259: 1 | S3259: 10282602241 | T3259: LOAYZA FLORES DANIEL GUIDO | U3259: 00 | V3259: =VLOOKUP(U3259,d_ff!A$1:B$5,2,0) -> 00: RECURSOS ORDINARIOS | W3259: 2.3. 2 9. 1 1 | X3259: =VLOOKUP(W3259,d_clasif!B$1:C$1529,2,0) -> 2.3. 2 9. 1 1: LOCACION DE SERVICIOS REALIZADOS POR PERSONAS NATURALES RELACIONADAS AL ROL DE LA ENTIDAD | Y3259: 47 | Z3259: Cadenas Presupuestal: 94=>9002=>3999999=>5000659=>22=>48=>109=>1=>44444=>27 Siaf/Ord: 415/217 | AA3259: 1250 | AB3259: 46185
A3260: 2026 | B3260: 416 | C3260: 2 | D3260: S | E3260: 296 | F3260: 218 | G3260: 94.02.13.06 | H3260: PLANTELES DE APLICACION GUAMAN POMA DE AYALA | I3260: 26 | J3260: IMPLEMENTACIÓN Y DESARROLLO DE LA EDUCACIÓN EN COLEGIOS EXPERIMENTALES | K3260: 7 | L3260: 11 | M3260: 38 | N3260: 899 | O3260: SERVICIOS ESPECIALIZADOS EN EDUCACION SECUNDARIA | P3260: SERVICIO | Q3260: 12500 | R3260: 1 | S3260: 10282732616 | T3260: BUITRON BERROCAL TULIO RAMIRO | U3260: 00 | V3260: =VLOOKUP(U3260,d_ff!A$1:B$5,2,0) -> 00: RECURSOS ORDINARIOS | W3260: 2.3. 2 9. 1 1 | X3260: =VLOOKUP(W3260,d_clasif!B$1:C$1529,2,0) -> 2.3. 2 9. 1 1: LOCACION DE SERVICIOS REALIZADOS POR PERSONAS NATURALES RELACIONADAS AL ROL DE LA ENTIDAD | Y3260: 47 | Z3260: Cadenas Presupuestal: 94=>9002=>3999999=>5000659=>22=>48=>109=>1=>44444=>27 Siaf/Ord: 416/218 | AA3260: 2500 | AB3260: 46174
A3261: 2026 | B3261: 416 | C3261: 2 | D3261: S | E3261: 296 | F3261: 218 | G3261: 94.02.13.06 | H3261: PLANTELES DE APLICACION GUAMAN POMA DE AYALA | I3261: 26 | J3261: IMPLEMENTACIÓN Y DESARROLLO DE LA EDUCACIÓN EN COLEGIOS EXPERIMENTALES | K3261: 7 | L3261: 11 | M3261: 38 | N3261: 899 | O3261: SERVICIOS ESPECIALIZADOS EN EDUCACION SECUNDARIA | P3261: SERVICIO | Q3261: 12500 | R3261: 1 | S3261: 10282732616 | T3261: BUITRON BERROCAL TULIO RAMIRO | U3261: 00 | V3261: =VLOOKUP(U3261,d_ff!A$1:B$5,2,0) -> 00: RECURSOS ORDINARIOS | W3261: 2.3. 2 9. 1 1 | X3261: =VLOOKUP(W3261,d_clasif!B$1:C$1529,2,0) -> 2.3. 2 9. 1 1: LOCACION DE SERVICIOS REALIZADOS POR PERSONAS NATURALES RELACIONADAS AL ROL DE LA ENTIDAD | Y3261: 47 | Z3261: Cadenas Presupuestal: 94=>9002=>3999999=>5000659=>22=>48=>109=>1=>44444=>27 Siaf/Ord: 416/218 | AA3261: 2500 | AB3261: 46185
A3262: 2026 | B3262: 417 | C3262: 2 | D3262: S | E3262: 297 | F3262: 220 | G3262: 94.02.13.06 | H3262: PLANTELES DE APLICACION GUAMAN POMA DE AYALA | I3262: 26 | J3262: IMPLEMENTACIÓN Y DESARROLLO DE LA EDUCACIÓN EN COLEGIOS EXPERIMENTALES | K3262: 7 | L3262: 11 | M3262: 44 | N3262: 608 | O3262: SERVICIO DE ASISTENCIA TECNICA Y ORIENTACION EN AUXILIAR EN EDUCACION | P3262: SERVICIO | Q3262: 10000 | R3262: 1 | S3262: 10283163810 | T3262: OCHANTE APAICO ROSA | U3262: 00 | V3262: =VLOOKUP(U3262,d_ff!A$1:B$5,2,0) -> 00: RECURSOS ORDINARIOS | W3262: 2.3. 2 9. 1 1 | X3262: =VLOOKUP(W3262,d_clasif!B$1:C$1529,2,0) -> 2.3. 2 9. 1 1: LOCACION DE SERVICIOS REALIZADOS POR PERSONAS NATURALES RELACIONADAS AL ROL DE LA ENTIDAD | Y3262: 47 | Z3262: Cadenas Presupuestal: 94=>9002=>3999999=>5000659=>22=>48=>109=>1=>44444=>27 Siaf/Ord: 417/220 | AA3262: 2000 | AB3262: 46185
A3263: 2026 | B3263: 418 | C3263: 2 | D3263: S | E3263: 298 | F3263: 221 | G3263: 94.02.13.06 | H3263: PLANTELES DE APLICACION GUAMAN POMA DE AYALA | I3263: 26 | J3263: IMPLEMENTACIÓN Y DESARROLLO DE LA EDUCACIÓN EN COLEGIOS EXPERIMENTALES | K3263: 7 | L3263: 5 | M3263: 4 | N3263: 16 | O3263: SERVICIO ESPECIALIZADO EN PSICOLOGIA | P3263: SERVICIO | Q3263: 10000 | R3263: 1 | S3263: 10739071955 | T3263: GUTIERREZ GAMBOA KELLY ALISSON | U3263: 00 | V3263: =VLOOKUP(U3263,d_ff!A$1:B$5,2,0) -> 00: RECURSOS ORDINARIOS | W3263: 2.3. 2 9. 1 1 | X3263: =VLOOKUP(W3263,d_clasif!B$1:C$1529,2,0) -> 2.3. 2 9. 1 1: LOCACION DE SERVICIOS REALIZADOS POR PERSONAS NATURALES RELACIONADAS AL ROL DE LA ENTIDAD | Y3263: 47 | Z3263: Cadenas Presupuestal: 94=>9002=>3999999=>5000659=>22=>48=>109=>1=>44444=>27 Siaf/Ord: 418/221 | AA3263: 2000 | AB3263: 46185
... A3318: 2026 | B3318: 1591 | C3318: 2 | D3318: S | E3318: 1231 | F3318: 827 | G3318: 94.02.08.07 | H3318: UNIDAD EJECUTORA DE INVERSIONES | I3318: 403 | J3318: MANTENIMIENTO DE LOS AMBIENTES DEL PABELLON N DE LA ESCUELA DE INGENIERIA CIVIL DE LA UNSCH | K3318: 60 | L3318: 35 | M3318: 2 | N3318: 54 | O3318: MANTENIMIENTO PREVENTIVO DE MOBILIARIO DE OFICINA | P3318: SERVICIO | Q3318: 4320 | R3318: 1 | S3318: 10282952888 | T3318: TUDELA HUAMAN LEONILDA | U3318: 13 | V3318: =VLOOKUP(U3318,d_ff!A$1:B$5,2,0) -> 13: DONACIONES Y TRANSFERENCIAS | W3318: 2.3. 2 4. 6 1 | X3318: =VLOOKUP(W3318,d_clasif!B$1:C$1529,2,0) -> 2.3. 2 4. 6 1: DE MOBILIARIO Y SIMILARES | Y3318: 81 | Z3318: Cadenas Presupuestal: 94=>9002=>3999999=>5000993=>22=>9=>109=>1=>1119=>1 Siaf/Ord: 1591/827 | AA3318: 4320 | AB3318: 46185
A3319: 2026 | B3319: 1405 | C3319: 2 | D3319: S | E3319: 1057 | F3319: 721 | G3319: 94.02.08.07 | H3319: UNIDAD EJECUTORA DE INVERSIONES | I3319: 381 | J3319: MEJORAM Y AMPLIAC DEL SERV DE GESTION INSTIT EN EL SISTEMA DE VIDEO VIGILANCIA Y CONTROL DE ACCESO DE PERSONAS EN LA CIUDAD UNIVERSITARIA DE LA UNSCH | O3319: SERVICIO DE PLOTEO Y SERVICIO DE FOTOCOPIADO | P3319: SERVICIO | Q3319: 1200 | R3319: 1 | S3319: 10282971807 | T3319: GALINDO VILCHEZ LIZBETH | U3319: 00 | V3319: =VLOOKUP(U3319,d_ff!A$1:B$5,2,0) -> 00: RECURSOS ORDINARIOS | W3319: 2.6. 2 2. 2 5 | X3319: =VLOOKUP(W3319,d_clasif!B$1:C$1529,2,0) -> 2.6. 2 2. 2 5: COSTO DE CONSTRUCCION POR ADMINISTRACION DIRECTA - SERVICIOS | Y3319: 63 | Z3319: Cadenas Presupuestal: 94=>66=>2534035=>4000040=>22=>48=>10=>1=>37703=>1 Siaf/Ord: 1405/721 | AA3319: 1320 | AB3319: 46189
A3320: 2026 | B3320: 1159 | C3320: 2 | D3320: S | E3320: 901 | F3320: 611 | G3320: 94.02.08.07 | H3320: UNIDAD EJECUTORA DE INVERSIONES | I3320: 381 | J3320: MEJORAM Y AMPLIAC DEL SERV DE GESTION INSTIT EN EL SISTEMA DE VIDEO VIGILANCIA Y CONTROL DE ACCESO DE PERSONAS EN LA CIUDAD UNIVERSITARIA DE LA UNSCH | O3320: SERVICIO DE PLOTEO Y SERVICIO DE FOTOCOPIADO | P3320: SERVICIO | Q3320: 1200 | R3320: 1 | S3320: 10282971807 | T3320: GALINDO VILCHEZ LIZBETH | U3320: 00 | V3320: =VLOOKUP(U3320,d_ff!A$1:B$5,2,0) -> 00: RECURSOS ORDINARIOS | W3320: 2.6. 2 2. 2 5 | X3320: =VLOOKUP(W3320,d_clasif!B$1:C$1529,2,0) -> 2.6. 2 2. 2 5: COSTO DE CONSTRUCCION POR ADMINISTRACION DIRECTA - SERVICIOS | Y3320: 63 | Z3320: Cadenas Presupuestal: 94=>66=>2534035=>4000040=>22=>48=>10=>1=>37703=>1 Siaf/Ord: 1159/611 | AA3320: 1370 | AB3320: 46164
A3321: 2026 | B3321: 1160 | C3321: 2 | D3321: S | E3321: 902 | F3321: 613 | G3321: 94.02.08.07 | H3321: UNIDAD EJECUTORA DE INVERSIONES | I3321: 380 | J3321: EJEC DEL PROY MEJORAMIENTO DEL SERVICIO DE GESTION INSTITUCIONAL EN EDUCACION SUPERIOR UNIVERSITARIA EN SERVICIOS BASICOS Y URBANISTICOS DE LA UNSCH | O3321: SERVICIO DE PLOTEO Y SERVICIO DE FOTOCOPIADO | P3321: SERVICIO | Q3321: 320 | R3321: 1 | S3321: 10282971807 | T3321: GALINDO VILCHEZ LIZBETH | U3321: 18 | V3321: =VLOOKUP(U3321,d_ff!A$1:B$5,2,0) -> 18: CANON Y SOBRECANON, REGALIAS, RENTA DE ADUANAS Y PARTICIPACIONES | W3321: 2.6. 2 2. 2 5 | X3321: =VLOOKUP(W3321,d_clasif!B$1:C$1529,2,0) -> 2.6. 2 2. 2 5: COSTO DE CONSTRUCCION POR ADMINISTRACION DIRECTA - SERVICIOS | Y3321: 65 | Z3321: Cadenas Presupuestal: 94=>66=>2644228=>4000040=>22=>48=>109=>1=>1508=>1 Siaf/Ord: 1160/613 | AA3321: 1320 | AB3321: 46174
A3322: 2026 | B3322: 1330 | C3322: 2 | D3322: S | E3322: 999 | F3322: 682 | G3322: 94.02.08.07 | H3322: UNIDAD EJECUTORA DE INVERSIONES | I3322: 403 | J3322: MANTENIMIENTO DE LOS AMBIENTES DEL PABELLON N DE LA ESCUELA DE INGENIERIA CIVIL DE LA UNSCH | K3322: 52 | L3322: 60 | M3322: 13 | N3322: 27 | O3322: INSTALACION DE VIDRIOS, INSTALACION DE VENTANA Y INSTALACION DE PUERTA BATIENTE | P3322: SERVICIO | Q3322: 3415 | R3322: 1 | S3322: 10700452307 | T3322: HUAMANI ORELLANA DAILY MASSIEL | U3322: 13 | V3322: =VLOOKUP(U3322,d_ff!A$1:B$5,2,0) -> 13: DONACIONES Y TRANSFERENCIAS | W3322: 2.3. 2 4. 2 1 | X3322: =VLOOKUP(W3322,d_clasif!B$1:C$1529,2,0) -> 2.3. 2 4. 2 1: DE EDIFICACIONES, OFICINAS Y ESTRUCTURAS | Y3322: 81 | Z3322: Cadenas Presupuestal: 94=>9002=>3999999=>5000993=>22=>9=>109=>1=>1119=>1 Siaf/Ord: 1330/682 | AA3322: 5975 | AB3322: 46182
A3323: 2026 | B3323: 1563 | C3323: 2 | D3323: S | E3323: 1189 | F3323: 788 | G3323: 94.02.08.07 | H3323: UNIDAD EJECUTORA DE INVERSIONES | I3323: 403 | J3323: MANTENIMIENTO DE LOS AMBIENTES DEL PABELLON N DE LA ESCUELA DE INGENIERIA CIVIL DE LA UNSCH | K3323: 60 | L3323: 1 | M3323: 1 | N3323: 35 | O3323: MANTENIMIENTO CORRECTIVO DE INSTALACIONES SANITARIAS, MANTENIMIENTO CORRECTIVO DE AMBIENTE Y MATENIMIENTO CORRECTIVO DE SISTEMA ELECTRICO | P3323: SERVICIO | Q3323: 1200 | R3323: 1 | S3323: 10423380034 | T3323: PINZAS GUTIERREZ JORGE LUIS | U3323: 13 | V3323: =VLOOKUP(U3323,d_ff!A$1:B$5,2,0) -> 13: DONACIONES Y TRANSFERENCIAS | W3323: 2.3. 2 4. 2 1 | X3323: =VLOOKUP(W3323,d_clasif!B$1:C$1529,2,0) -> 2.3. 2 4. 2 1: DE EDIFICACIONES, OFICINAS Y ESTRUCTURAS | Y3323: 81 | Z3323: Cadenas Presupuestal: 94=>9002=>3999999=>5000993=>22=>9=>109=>1=>1119=>1 Siaf/Ord: 1563/788 | AA3323: 11500 | AB3323: 46182
A3324: 2026 | B3324: 19 | C3324: 2 | D3324: V | E3324: 8 | F3324: 5 | G3324: 94.02.05 | H3324: OFICINA DE COOPERACIÓN Y RELACIONES INTERNACIONALES | I3324: 167 | J3324: IMPLEMENTACIÓN DEL PROCESO DE INTERNACIONALIZACION DE LA UNIVERSIDAD | O3324: APOYO ECONOMICO POR CONCEPTO DE VIÁTICOS INTERNACIONALES A ESPAÑA E ITALIA DEL 27 DE ENERO AL 15 DE FEBRERO DE 2026 NTD 2608328 A FAVOR DE ANDRES MOISES HUAYANAY QUISPE A FIN DE PARTICIPAR EN EL PROCESO DE FORMACION E IMPLEMENTACION DE LA MAESTRIA EN INNO | U3324: 00 | V3324: =VLOOKUP(U3324,d_ff!A$1:B$5,2,0) -> 00: RECURSOS ORDINARIOS | W3324: 2.3. 2 1. 1 2 | X3324: =VLOOKUP(W3324,d_clasif!B$1:C$1529,2,0) -> 2.3. 2 1. 1 2: VIATICOS Y ASIGNACIONES POR COMISION DE SERVICIO | Y3324: 29 | Z3324: Cadenas Presupuestal: 94=>9001=>3999999=>5000002=>22=>6=>7=>2=>542=>43 Siaf/Ord: 19/5 | AA3324: 16999.8 | AB3324: 46045
A3325: 2026 | B3325: 22 | C3325: 2 | D3325: V | E3325: 8 | F3325: 8 | G3325: 94.02.05 | H3325: OFICINA DE COOPERACIÓN Y RELACIONES INTERNACIONALES | I3325: 167 | J3325: IMPLEMENTACIÓN DEL PROCESO DE INTERNACIONALIZACION DE LA UNIVERSIDAD | O3325: APOYO ECONOMICO POR CONCEPTO DE VIÁTICOS INTERNACIONALES A ESPAÑA E ITALIA DEL 27 DE ENERO AL 15 DE FEBRERO DE 2026 NTD 2608328 A FAVOR DE OSCAR AMERICO VALLEJOS SAENZ A FIN DE PARTICIPAR EN EL PROCESO DE FORMACION E IMPLEMENTACION DE LA MAESTRIA EN INNOV | U3325: 00 | V3325: =VLOOKUP(U3325,d_ff!A$1:B$5,2,0) -> 00: RECURSOS ORDINARIOS | W3325: 2.3. 2 1. 1 2 | X3325: =VLOOKUP(W3325,d_clasif!B$1:C$1529,2,0) -> 2.3. 2 1. 1 2: VIATICOS Y ASIGNACIONES POR COMISION DE SERVICIO | Y3325: 29 | Z3325: Cadenas Presupuestal: 94=>9001=>3999999=>5000002=>22=>6=>7=>2=>542=>43 Siaf/Ord: 22/8 | AA3325: 16999.8 | AB3325: 46045
A3326: 2026 | B3326: 25 | C3326: 2 | D3326: V | E3326: 8 | F3326: 11 | G3326: 94.02.05 | H3326: OFICINA DE COOPERACIÓN Y RELACIONES INTERNACIONALES | I3326: 167 | J3326: IMPLEMENTACIÓN DEL PROCESO DE INTERNACIONALIZACION DE LA UNIVERSIDAD | O3326: APOYO ECONOMICO POR CONCEPTO DE VIÁTICOS INTERNACIONALES A ESPAÑA E ITALIA DEL 27 DE ENERO AL 15 DE FEBRERO DE 2026 NTD 2608328 A FAVOR DE LOURDES MEDINA MORALES A FIN DE PARTICIPAR EN EL PROCESO DE FORMACION E IMPLEMENTACION DE LA MAESTRIA EN INNOVACION | U3326: 00 | V3326: =VLOOKUP(U3326,d_ff!A$1:B$5,2,0) -> 00: RECURSOS ORDINARIOS | W3326: 2.3. 2 1. 1 2 | X3326: =VLOOKUP(W3326,d_clasif!B$1:C$1529,2,0) -> 2.3. 2 1. 1 2: VIATICOS Y ASIGNACIONES POR COMISION DE SERVICIO | Y3326: 29 | Z3326: Cadenas Presupuestal: 94=>9001=>3999999=>5000002=>22=>6=>7=>2=>542=>43 Siaf/Ord: 25/11 | AA3326: 16999.8 | AB3326: 46045
A3327: 2026 | B3327: 28 | C3327: 2 | D3327: V | E3327: 8 | F3327: 14 | G3327: 94.02.05 | H3327: OFICINA DE COOPERACIÓN Y RELACIONES INTERNACIONALES | I3327: 167 | J3327: IMPLEMENTACIÓN DEL PROCESO DE INTERNACIONALIZACION DE LA UNIVERSIDAD | O3327: APOYO ECONOMICO POR CONCEPTO DE VIÁTICOS INTERNACIONALES A ESPAÑA E ITALIA DEL 27 DE ENERO AL 15 DE FEBRERO DE 2026 NTD 2608328 A FAVOR DE AURORA ISHEVIT VARGAS TOLEDO A FIN DE PARTICIPAR EN EL PROCESO DE FORMACION E IMPLEMENTACION DE LA MAESTRIA EN INNOV | U3327: 00 | V3327: =VLOOKUP(U3327,d_ff!A$1:B$5,2,0) -> 00: RECURSOS ORDINARIOS | W3327: 2.3. 2 1. 1 2 | X3327: =VLOOKUP(W3327,d_clasif!B$1:C$1529,2,0) -> 2.3. 2 1. 1 2: VIATICOS Y ASIGNACIONES POR COMISION DE SERVICIO | Y3327: 29 | Z3327: Cadenas Presupuestal: 94=>9001=>3999999=>5000002=>22=>6=>7=>2=>542=>43 Siaf/Ord: 28/14 | AA3327: 16999.8 | AB3327: 46045
A3328: 2026 | B3328: 33 | C3328: 2 | D3328: V | E3328: 8 | F3328: 17 | G3328: 94.02.05 | H3328: OFICINA DE COOPERACIÓN Y RELACIONES INTERNACIONALES | I3328: 167 | J3328: IMPLEMENTACIÓN DEL PROCESO DE INTERNACIONALIZACION DE LA UNIVERSIDAD | O3328: APOYO ECONOMICO DE VIATICOS PARA LA CIUDAD DE LIMA EL 16/02/2026 NTD 2608328 A FAVOR DE PELAYO HILARIO VALENZUELA PARA TRASLADO DE ESPAÑA LUEGO DE SU PARTICIPACION EN EL PROCESO DE FORMACION E IMPLEMENTACION DE LA MAESTRIA EN INNOVACION PARA EL DESARROLLO | U3328: 00 | V3328: =VLOOKUP(U3328,d_ff!A$1:B$5,2,0) -> 00: RECURSOS ORDINARIOS | W3328: 2.3. 2 1. 1 2 | X3328: =VLOOKUP(W3328,d_clasif!B$1:C$1529,2,0) -> 2.3. 2 1. 1 2: VIATICOS Y ASIGNACIONES POR COMISION DE SERVICIO | Y3328: 29 | Z3328: Cadenas Presupuestal: 94=>9001=>3999999=>5000002=>22=>6=>7=>2=>542=>43 Siaf/Ord: 33/17 | AA3328: 16999.8 | AB3328: 46045
A3329: 2026 | B3329: 20 | C3329: 2 | D3329: V | E3329: 7 | F3329: 6 | G3329: 94.02.05 | H3329: OFICINA DE COOPERACIÓN Y RELACIONES INTERNACIONALES | I3329: 167 | J3329: IMPLEMENTACIÓN DEL PROCESO DE INTERNACIONALIZACION DE LA UNIVERSIDAD | O3329: APOYO ECONOMICO DE VIATICOS PARA LA CIUDAD DE LIMA EL 16/02/2026 NTD 2608328 A FAVOR DE ANDRES MOISES HUAYANAY QUISPE PARA TRASLADO DE ESPAÑA LUEGO DE SU PARTICIPACION EN EL PROCESO DE FORMACION E IMPLEMENTACION DE LA MAESTRIA EN INNOVACION PARA EL DESARR | U3329: 00 | V3329: =VLOOKUP(U3329,d_ff!A$1:B$5,2,0) -> 00: RECURSOS ORDINARIOS | W3329: 2.3. 2 1. 2 2 | X3329: =VLOOKUP(W3329,d_clasif!B$1:C$1529,2,0) -> 2.3. 2 1. 2 2: VIATICOS Y ASIGNACIONES POR COMISION DE SERVICIO | Y3329: 29 | Z3329: Cadenas Presupuestal: 94=>9001=>3999999=>5000002=>22=>6=>7=>2=>542=>43 Siaf/Ord: 20/6 | AA3329: 200 | AB3329: 46045
A3330: 2026 | B3330: 21 | C3330: 2 | D3330: V | E3330: 7 | F3330: 7 | G3330: 94.02.05 | H3330: OFICINA DE COOPERACIÓN Y RELACIONES INTERNACIONALES | I3330: 167 | J3330: IMPLEMENTACIÓN DEL PROCESO DE INTERNACIONALIZACION DE LA UNIVERSIDAD | O3330: APOYO ECONOMICO DE VIATICOS PARA LA CIUDAD DE LIMA EL 26/01/2026 NTD 2608328 A FAVOR DE OSCAR AMERICO VALLEJOS SAENZ A FIN TRASLADARSE A ESPAÑA E ITALIA A FIN DE PARTICIPAR EN EL PROCESO DE FORMACION E IMPLEMENTACION DE LA MAESTRIA EN INNOVACION PARA EL D | U3330: 00 | V3330: =VLOOKUP(U3330,d_ff!A$1:B$5,2,0) -> 00: RECURSOS ORDINARIOS | W3330: 2.3. 2 1. 2 2 | X3330: =VLOOKUP(W3330,d_clasif!B$1:C$1529,2,0) -> 2.3. 2 1. 2 2: VIATICOS Y ASIGNACIONES POR COMISION DE SERVICIO | Y3330: 29 | Z3330: Cadenas Presupuestal: 94=>9001=>3999999=>5000002=>22=>6=>7=>2=>542=>43 Siaf/Ord: 21/7 | AA3330: 200 | AB3330: 46045
A3331: 2026 | B3331: 23 | C3331: 2 | D3331: V | E3331: 7 | F3331: 9 | G3331: 94.02.05 | H3331: OFICINA DE COOPERACIÓN Y RELACIONES INTERNACIONALES | I3331: 167 | J3331: IMPLEMENTACIÓN DEL PROCESO DE INTERNACIONALIZACION DE LA UNIVERSIDAD | O3331: APOYO ECONOMICO DE VIATICOS PARA LA CIUDAD DE LIMA EL 16/02/2026 NTD 2608328 A FAVOR DE OSCAR AMERICO VALLEJOS SAENZ PARA TRASLADO DE ESPAÑA LUEGO DE SU PARTICIPACION EN EL PROCESO DE FORMACION E IMPLEMENTACION DE LA MAESTRIA EN INNOVACION PARA EL DESARRO | U3331: 00 | V3331: =VLOOKUP(U3331,d_ff!A$1:B$5,2,0) -> 00: RECURSOS ORDINARIOS | W3331: 2.3. 2 1. 2 2 | X3331: =VLOOKUP(W3331,d_clasif!B$1:C$1529,2,0) -> 2.3. 2 1. 2 2: VIATICOS Y ASIGNACIONES POR COMISION DE SERVICIO | Y3331: 29 | Z3331: Cadenas Presupuestal: 94=>9001=>3999999=>5000002=>22=>6=>7=>2=>542=>43 Siaf/Ord: 23/9 | AA3331: 200 | AB3331: 46045
A3332: 2026 | B3332: 24 | C3332: 2 | D3332: V | E3332: 7 | F3332: 10 | G3332: 94.02.05 | H3332: OFICINA DE COOPERACIÓN Y RELACIONES INTERNACIONALES | I3332: 167 | J3332: IMPLEMENTACIÓN DEL PROCESO DE INTERNACIONALIZACION DE LA UNIVERSIDAD | O3332: APOYO ECONOMICO DE VIATICOS PARA LA CIUDAD DE LIMA EL 26/01/2026 NTD 2608328 A FAVOR DE LOURDES MEDINA MORALES A FIN TRASLADARSE A ESPAÑA E ITALIA A FIN DE PARTICIPAR EN EL PROCESO DE FORMACION E IMPLEMENTACION DE LA MAESTRIA EN INNOVACION PARA EL DESARRO | U3332: 00 | V3332: =VLOOKUP(U3332,d_ff!A$1:B$5,2,0) -> 00: RECURSOS ORDINARIOS | W3332: 2.3. 2 1. 2 2 | X3332: =VLOOKUP(W3332,d_clasif!B$1:C$1529,2,0) -> 2.3. 2 1. 2 2: VIATICOS Y ASIGNACIONES POR COMISION DE SERVICIO | Y3332: 29 | Z3332: Cadenas Presupuestal: 94=>9001=>3999999=>5000002=>22=>6=>7=>2=>542=>43 Siaf/Ord: 24/10 | AA3332: 200 | AB3332: 46045
A3333: 2026 | B3333: 26 | C3333: 2 | D3333: V | E3333: 7 | F3333: 12 | G3333: 94.02.05 | H3333: OFICINA DE COOPERACIÓN Y RELACIONES INTERNACIONALES | I3333: 167 | J3333: IMPLEMENTACIÓN DEL PROCESO DE INTERNACIONALIZACION DE LA UNIVERSIDAD | O3333: APOYO ECONOMICO DE VIATICOS PARA LA CIUDAD DE LIMA EL 16/02/2026 NTD 2608328 A FAVOR DE LOURDES MEDINA MORALES PARA TRASLADO DE ESPAÑA LUEGO DE SU PARTICIPACION EN EL PROCESO DE FORMACION E IMPLEMENTACION DE LA MAESTRIA EN INNOVACION PARA EL DESARROLLO SO | U3333: 00 | V3333: =VLOOKUP(U3333,d_ff!A$1:B$5,2,0) -> 00: RECURSOS ORDINARIOS | W3333: 2.3. 2 1. 2 2 | X3333: =VLOOKUP(W3333,d_clasif!B$1:C$1529,2,0) -> 2.3. 2 1. 2 2: VIATICOS Y ASIGNACIONES POR COMISION DE SERVICIO | Y3333: 29 | Z3333: Cadenas Presupuestal: 94=>9001=>3999999=>5000002=>22=>6=>7=>2=>542=>43 Siaf/Ord: 26/12 | AA3333: 200 | AB3333: 46045
A3334: 2026 | B3334: 27 | C3334: 2 | D3334: V | E3334: 7 | F3334: 13 | G3334: 94.02.05 | H3334: OFICINA DE COOPERACIÓN Y RELACIONES INTERNACIONALES | I3334: 167 | J3334: IMPLEMENTACIÓN DEL PROCESO DE INTERNACIONALIZACION DE LA UNIVERSIDAD | O3334: APOYO ECONOMICO DE VIATICOS PARA LA CIUDAD DE LIMA EL 26/01/2026 NTD 2608328 A FAVOR DE AURORA ISHEVIT VARGAS TOLEDO A FIN TRASLADARSE A ESPAÑA E ITALIA A FIN DE PARTICIPAR EN EL PROCESO DE FORMACION E IMPLEMENTACION DE LA MAESTRIA EN INNOVACION PARA EL D | U3334: 00 | V3334: =VLOOKUP(U3334,d_ff!A$1:B$5,2,0) -> 00: RECURSOS ORDINARIOS | W3334: 2.3. 2 1. 2 2 | X3334: =VLOOKUP(W3334,d_clasif!B$1:C$1529,2,0) -> 2.3. 2 1. 2 2: VIATICOS Y ASIGNACIONES POR COMISION DE SERVICIO | Y3334: 29 | Z3334: Cadenas Presupuestal: 94=>9001=>3999999=>5000002=>22=>6=>7=>2=>542=>43 Siaf/Ord: 27/13 | AA3334: 200 | AB3334: 46045
A3335: 2026 | B3335: 29 | C3335: 2 | D3335: V | E3335: 7 | F3335: 15 | G3335: 94.02.05 | H3335: OFICINA DE COOPERACIÓN Y RELACIONES INTERNACIONALES | I3335: 167 | J3335: IMPLEMENTACIÓN DEL PROCESO DE INTERNACIONALIZACION DE LA UNIVERSIDAD | O3335: APOYO ECONOMICO DE VIATICOS PARA LA CIUDAD DE LIMA EL 16/02/2026 NTD 2608328 A FAVOR DE AURORA ISHEVIT VARGAS TOLEDO PARA TRASLADO DE ESPAÑA LUEGO DE SU PARTICIPACION EN EL PROCESO DE FORMACION E IMPLEMENTACION DE LA MAESTRIA EN INNOVACION PARA EL DESARRO | U3335: 00 | V3335: =VLOOKUP(U3335,d_ff!A$1:B$5,2,0) -> 00: RECURSOS ORDINARIOS | W3335: 2.3. 2 1. 2 2 | X3335: =VLOOKUP(W3335,d_clasif!B$1:C$1529,2,0) -> 2.3. 2 1. 2 2: VIATICOS Y ASIGNACIONES POR COMISION DE SERVICIO | Y3335: 29 | Z3335: Cadenas Presupuestal: 94=>9001=>3999999=>5000002=>22=>6=>7=>2=>542=>43 Siaf/Ord: 29/15 | AA3335: 200 | AB3335: 46045
... A3568: 2026 | B3568: 1653 | C3568: 2 | D3568: V | E3568: 1287 | F3568: 111 | G3568: 94.02.17.02 | H3568: ESCUELA PROFESIONAL DE INGENIERIA QUIMICA | I3568: 152 | J3568: REALIZACIÓN DE VIAJE DE ESTUDIOS (E.P.INGENIERÍA QUÍMICA) | O3568: VIAJE DE ESTUDIOS DE LOS ESTUDIANTES EP DE INGENIERIA QUIMICA A REALIZARSE DEL 08 AL 17 DE JUNIO DE 2026 DOCENTE RESPONSABLE JORGE SOTERO GARCIA BLASQUEZ MOROTE, RR Nº 383-2026-UNSCH-R NTD 2672070 CON ITINERARIO: AYACUCHO-ICA-LIMA-ANCASH-LA LIBERTAD-LAMBA | U3568: 00 | V3568: =VLOOKUP(U3568,d_ff!A$1:B$5,2,0) -> 00: RECURSOS ORDINARIOS | W3568: 2.3. 1 3. 1 1 | X3568: =VLOOKUP(W3568,d_clasif!B$1:C$1529,2,0) -> 2.3. 1 3. 1 1: COMBUSTIBLES Y CARBURANTES | Y3568: 14 | Z3568: Cadenas Presupuestal: 94=>66=>3000784=>5005857=>22=>48=>109=>1=>188104=>43 Siaf/Ord: 1653/111 | AA3568: 6500 | AB3568: 46178
A3569: 2026 | B3569: 1671 | C3569: 2 | D3569: V | E3569: 1334 | F3569: 115 | G3569: 94.02.17.02 | H3569: ESCUELA PROFESIONAL DE INGENIERIA QUIMICA | I3569: 152 | J3569: REALIZACIÓN DE VIAJE DE ESTUDIOS (E.P.INGENIERÍA QUÍMICA) | O3569: VIAJE DE ESTUDIOS DE LOS ESTUDIANTES EP DE INGENIERIA QUIMICA A REALIZARSE DEL 08 AL 17 DE JUNIO DE 2026 DOCENTE RESPONSABLE LUIS ALBERTO COSSIO HERRERA, RR Nº 390-2026-UNSCH-R NTD 2673902 CON ITINERARIO: AYACUCHO-LIMA-CHALA-AREQUIPA NAZCA-AYACUCHO MATRIC | U3569: 00 | V3569: =VLOOKUP(U3569,d_ff!A$1:B$5,2,0) -> 00: RECURSOS ORDINARIOS | W3569: 2.3. 1 3. 1 1 | X3569: =VLOOKUP(W3569,d_clasif!B$1:C$1529,2,0) -> 2.3. 1 3. 1 1: COMBUSTIBLES Y CARBURANTES | Y3569: 14 | Z3569: Cadenas Presupuestal: 94=>66=>3000784=>5005857=>22=>48=>109=>1=>188104=>43 Siaf/Ord: 1671/115 | AB3569: 46178
A3570: 2026 | B3570: 1794 | C3570: 2 | D3570: V | E3570: 1452 | F3570: 127 | G3570: 94.02.12.03 | H3570: ESCUELA PROFESIONAL DE CONTABILIDAD Y AUDITORIA | I3570: 86 | J3570: REALIZACIÓN DE VIAJE DE ESTUDIO (EP CONTABILIDAD) | O3570: DOCENTE RESPONSABLE ENCARGO FONDO EDWAR RAFAEL ENCISO HUILLCA DE VIAJE DE ESTUDIOS DE LOS ESTUDIANTES DE LA EP DE CONTABILIDAD Y AUDITORIA DEL 15 AL 24 DE JUNIO DE 2026, RR 403-20265-UNSCH-R NTD 2677606 CON ITINERARIO: AYACUCHO-MOQUEGUA-ILO-TACNA-PUNO-ARE | U3570: 00 | V3570: =VLOOKUP(U3570,d_ff!A$1:B$5,2,0) -> 00: RECURSOS ORDINARIOS | W3570: 2.3. 1 3. 1 1 | X3570: =VLOOKUP(W3570,d_clasif!B$1:C$1529,2,0) -> 2.3. 1 3. 1 1: COMBUSTIBLES Y CARBURANTES | Y3570: 14 | Z3570: Cadenas Presupuestal: 94=>66=>3000784=>5005857=>22=>48=>109=>1=>188104=>43 Siaf/Ord: 1794/127 | AA3570: 7107.8 | AB3570: 46185
A3571: 2026 | B3571: 1865 | C3571: 2 | D3571: V | E3571: 1468 | F3571: 134 | G3571: 94.02.16.03 | H3571: ESCUELA PROFESIONAL DE INGENIERIA DE MINAS | I3571: 145 | J3571: REALIZACIÓN DE VIAJE DE ESTUDIO (EP INGENIERÍADE MINAS) | O3571: DOCENTE RESPONSABLE DEL ENCARGO EDMUNDO CAMPOS ARZAPALO DE VIAJE DE ESTUDIOS DE LOS ESTUDIANTES DE LA EP DE INGENIERIA DE MINAS DEL 18 AL 27 DE JUNIO DE 2026, RR 402-2026-UNSCH-R NTD 2677818 CON ITINERARIO: AYACUCHO-MINA COBRIZA-CATALINA HUANCA-AYACUCHO-A | U3571: 00 | V3571: =VLOOKUP(U3571,d_ff!A$1:B$5,2,0) -> 00: RECURSOS ORDINARIOS | W3571: 2.3. 1 3. 1 1 | X3571: =VLOOKUP(W3571,d_clasif!B$1:C$1529,2,0) -> 2.3. 1 3. 1 1: COMBUSTIBLES Y CARBURANTES | Y3571: 14 | Z3571: Cadenas Presupuestal: 94=>66=>3000784=>5005857=>22=>48=>109=>1=>188104=>43 Siaf/Ord: 1865/134 | AA3571: 5500 | AB3571: 46191
A3572: 2026 | B3572: 1868 | C3572: 2 | D3572: V | E3572: 1474 | F3572: 137 | G3572: 94.02.14.05 | H3572: ESCUELA PROFESIONAL DE CIENCIAS DE LA COMUNICACION | I3572: 161 | J3572: REALIZACIÓN DE VIAJE DE ESTUDIO (EP CIENCIAS DE LA COMUNICACIÓN) | O3572: DOCENTE RESPONSABLE DEL ENCARGO DE FONDO JOSE CARLOS ROMERO QUINTANILLA DEL VIAJE DE ESTUDIOS DE ALUMNOS DE EP DE CIENCIAS DE LA COMUNICACION DEL 15 AL 24 DE JUNIO DE 2026, RR Nº 406-2026-UNSCH-R NTD 2679212 CON ITINERARIO: AYACUCHO-CUSCO-PUNO-AREQUIPA-IC | U3572: 00 | V3572: =VLOOKUP(U3572,d_ff!A$1:B$5,2,0) -> 00: RECURSOS ORDINARIOS | W3572: 2.3. 1 3. 1 1 | X3572: =VLOOKUP(W3572,d_clasif!B$1:C$1529,2,0) -> 2.3. 1 3. 1 1: COMBUSTIBLES Y CARBURANTES | Y3572: 14 | Z3572: Cadenas Presupuestal: 94=>66=>3000784=>5005857=>22=>48=>109=>1=>188104=>43 Siaf/Ord: 1868/137 | AA3572: 3822.04 | AB3572: 46189
A3573: 2026 | B3573: 2022 | C3573: 2 | D3573: V | E3573: 1610 | F3573: 154 | G3573: 94.02.10.02 | H3573: ESCUELA PROFESIONAL DE AGRONOMIA | I3573: 3 | J3573: REALIZACIÓN DE VIAJE DE ESTUDIO (EP AGRONOMÍA) | O3573: DOCENTE RESPONSABLE DEL ENCARGO DE FONDO YURI GALVEZ GASTELU DEL VIAJE DE ESTUDIOS DE ALUMNOS DE EP DE AGRONOMIA DEL 30 DE JUNIO AL 09 DE JULIO DE 2026, RR Nº 416-2026-UNSCH-R NTD 2681616 CON ITINERARIO: AYACUCHO-CHINCHA-LIMA-HUARAL-TRUJILLO-CHICLAYO-CAJA | U3573: 00 | V3573: =VLOOKUP(U3573,d_ff!A$1:B$5,2,0) -> 00: RECURSOS ORDINARIOS | W3573: 2.3. 1 3. 1 1 | X3573: =VLOOKUP(W3573,d_clasif!B$1:C$1529,2,0) -> 2.3. 1 3. 1 1: COMBUSTIBLES Y CARBURANTES | Y3573: 14 | Z3573: Cadenas Presupuestal: 94=>66=>3000784=>5005857=>22=>48=>109=>1=>188104=>43 Siaf/Ord: 2022/154 | AA3573: 6997.4 | AB3573: 46196
A3574: 2026 | B3574: 1735 | C3574: 2 | D3574: V | E3574: 1390 | F3574: 120 | G3574: 94.02.16.02 | H3574: ESCUELA PROFESIONAL DE INGENIERIA DE SISTEMAS | I3574: 155 | J3574: REALIZACION DEL DESARROLLO DE CAPACITACION DOCENTE PARA LA MEJORA DE SU COMPETENCIA PARA LA ENSEÑANZA ACADEMICA (EP INGENIERÍA DE SISTEMAS) | O3574: VIAJE EN COMISION DE SERVICIO A FAVOR DE CELIA EDITH MARTINEZ CORDOVA A LA CIUDAD DE AREQUIPA EL 11 Y 12 DE JUNIO DE 2026 NTD 2670154 A FIN DE PARTICIPAR COMO EXPOSITOR EN EL 2DO EVENTO CIENTIFICO EXPO PORCINA PECUARIA 2026 VI EDICION | U3574: 00 | V3574: =VLOOKUP(U3574,d_ff!A$1:B$5,2,0) -> 00: RECURSOS ORDINARIOS | W3574: 2.3. 2 1. 2 1 | X3574: =VLOOKUP(W3574,d_clasif!B$1:C$1529,2,0) -> 2.3. 2 1. 2 1: PASAJES Y GASTOS DE TRANSPORTE | Y3574: 14 | Z3574: Cadenas Presupuestal: 94=>66=>3000784=>5005857=>22=>48=>109=>1=>188104=>43 Siaf/Ord: 1735/120 | AA3574: 200 | AB3574: 46183
A3575: 2026 | B3575: 1764 | C3575: 2 | D3575: V | E3575: 1437 | F3575: 124 | G3575: 94.02.16.05 | H3575: ESCUELA PROFESIONAL DE CIENCIAS FISICO MATEMATICA | I3575: 216 | J3575: REALIZACIÓN DEL DESARROLLO DE CAPACITACIÓN DOCENTE PARA LA MEJORA DE SUS COMPETENCIAS PARA ENSEÑANZA ACADÉMICA (EP. FISICO-MATEMATICO) | O3575: VIÁTICOS POR CAPACITACION A LA CIUDAD DE LIMA EL 16 y 17/06/2025 NTD 2670484 A FAVOR DE DIANA LUJAN PEREZ A FIN DE PARTICIPAR DEL II CONGRESO DE ESTADISTICA Y CIENCIAS DE DATOS 2026 ORGANIZADO POR EL PROGRAMA DE ESTUDIOS DE INGENIERÍA ESTADÍSTICA E INFORM | U3575: 00 | V3575: =VLOOKUP(U3575,d_ff!A$1:B$5,2,0) -> 00: RECURSOS ORDINARIOS | W3575: 2.3. 2 1. 2 1 | X3575: =VLOOKUP(W3575,d_clasif!B$1:C$1529,2,0) -> 2.3. 2 1. 2 1: PASAJES Y GASTOS DE TRANSPORTE | Y3575: 14 | Z3575: Cadenas Presupuestal: 94=>66=>3000784=>5005857=>22=>48=>109=>1=>188104=>43 Siaf/Ord: 1764/124 | AA3575: 100 | AB3575: 46185
A3576: 2026 | B3576: 1765 | C3576: 2 | D3576: V | E3576: 1437 | F3576: 125 | G3576: 94.02.16.05 | H3576: ESCUELA PROFESIONAL DE CIENCIAS FISICO MATEMATICA | I3576: 216 | J3576: REALIZACIÓN DEL DESARROLLO DE CAPACITACIÓN DOCENTE PARA LA MEJORA DE SUS COMPETENCIAS PARA ENSEÑANZA ACADÉMICA (EP. FISICO-MATEMATICO) | O3576: VIÁTICOS POR CAPACITACION A LA CIUDAD DE LIMA EL 16 y 17/06/2025 NTD 2665145 A FAVOR DEGUILLERMO BERNARDINO TAPIA CALDERON A FIN DE PARTICIPAR DEL II CONGRESO DE ESTADISTICA Y CIENCIAS DE DATOS 2026 ORGANIZADO POR EL PROGRAMA DE ESTUDIOS DE INGENIERÍA EST | U3576: 00 | V3576: =VLOOKUP(U3576,d_ff!A$1:B$5,2,0) -> 00: RECURSOS ORDINARIOS | W3576: 2.3. 2 1. 2 1 | X3576: =VLOOKUP(W3576,d_clasif!B$1:C$1529,2,0) -> 2.3. 2 1. 2 1: PASAJES Y GASTOS DE TRANSPORTE | Y3576: 14 | Z3576: Cadenas Presupuestal: 94=>66=>3000784=>5005857=>22=>48=>109=>1=>188104=>43 Siaf/Ord: 1765/125 | AA3576: 100 | AB3576: 46185
A3577: 2026 | B3577: 1797 | C3577: 2 | D3577: V | E3577: 1436 | F3577: 130 | G3577: 94.02.16.04 | H3577: ESCUELA PROFESIONAL DE INGENIERIA CIVIL | I3577: 75 | J3577: IMPLEMENTACIÓN DEL FORTALECIMIENTO DE CAPACIDADES DEL PERSONAL ADMINISTRATIVO (EP.CIVIL) | O3577: VIAJE EN COMISION DE SERVICIO A LA CIUDAD DE ANDAHUAYLAS LOS DIAS 16 Y 17 DE JUNIO 2026 NTD 2675501 A FAVOR DE ALEX SANDER IRCAÑAUPA HUAMANI A FIN DE PARTICIPAR EN EL II CONGRESO NACIONAL DE INGENIERÍA CIVIL ORGANIZADO POR LA UNIVERSIDAD NACIONAL JOSÉ MAR | U3577: 00 | V3577: =VLOOKUP(U3577,d_ff!A$1:B$5,2,0) -> 00: RECURSOS ORDINARIOS | W3577: 2.3. 2 1. 2 1 | X3577: =VLOOKUP(W3577,d_clasif!B$1:C$1529,2,0) -> 2.3. 2 1. 2 1: PASAJES Y GASTOS DE TRANSPORTE | Y3577: 14 | Z3577: Cadenas Presupuestal: 94=>66=>3000784=>5005857=>22=>48=>109=>1=>188104=>43 Siaf/Ord: 1797/130 | AA3577: 120 | AB3577: 46189
A3578: 2026 | B3578: 1972 | C3578: 2 | D3578: V | E3578: 1565 | F3578: 151 | G3578: 94.02.10.04 | H3578: ESCUELA PROFESIONAL DE INGENIERIA AGROFORESTAL | I3578: 9 | J3578: IMPLEMENTACIÓN PARA LA ATENCION DE CATEDRA, ASESORAMIENTO Y TUTORIA AL ESTUDIANTE | O3578: VIAJE EN COMISION DE SERVICIO A FAVOR DE CARLOS ORLANDO HUAYHUA LOBATON A LA CIUDAD DE AYACUCHO EL 24 Y 25/06/2026 NTD 2680709 A FIN DE PARTICIPAR EN LA SEGUNDA JORNADA DE ACOMPAÑAMIENTO EN EL PROCESO DE ELABORACIÓN DEL NUEVO CURRÍCULO CORRESPONDIENTE A L | U3578: 00 | V3578: =VLOOKUP(U3578,d_ff!A$1:B$5,2,0) -> 00: RECURSOS ORDINARIOS | W3578: 2.3. 2 1. 2 1 | X3578: =VLOOKUP(W3578,d_clasif!B$1:C$1529,2,0) -> 2.3. 2 1. 2 1: PASAJES Y GASTOS DE TRANSPORTE | Y3578: 14 | Z3578: Cadenas Presupuestal: 94=>66=>3000784=>5005857=>22=>48=>109=>1=>188104=>43 Siaf/Ord: 1972/151 | AA3578: 200 | AB3578: 46196
...

Sheet d_ff
A1: fuente_financ | B1: nombre_ff
A2: 00 | B2: 00: RECURSOS ORDINARIOS
A3: 09 | B3: 09: RECURSOS DIRECTAMENTE RECAUDADOS
A4: 18 | B4: 18: CANON Y SOBRECANON, REGALIAS, RENTA DE ADUANAS Y PARTICIPACIONES
A5: 13 | B5: 13: DONACIONES Y TRANSFERENCIAS

Sheet d_clasif
A1: CLASIFICADOR | B1: CLASIFICADOR | C1: NOMBRE_CLASIF
A2: 1.1.1.1.1.1 | B2: 1.1. 1 1. 1 1 | C2: 1.1. 1 1. 1 1: RENTA DE TERCERA CATEGORIA
A3: 1.1.1.1.2.1 | B3: 1.1. 1 1. 2 1 | C3: 1.1. 1 1. 2 1: RENTA DE PRIMERA CATEGORIA
A4: 1.1.1.1.2.2 | B4: 1.1. 1 1. 2 2 | C4: 1.1. 1 1. 2 2: RENTA DE SEGUNDA CATEGORIA
A5: 1.1.1.1.2.3 | B5: 1.1. 1 1. 2 3 | C5: 1.1. 1 1. 2 3: RENTA DE CUARTA CATEGORIA
A6: 1.1.1.1.2.4 | B6: 1.1. 1 1. 2 4 | C6: 1.1. 1 1. 2 4: RENTA DE QUINTA CATEGORIA
A7: 1.1.1.2.1.1 | B7: 1.1. 1 2. 1 1 | C7: 1.1. 1 2. 1 1: IMPUESTO A LA RENTA DE NO DOMICILIADOS
A8: 1.1.1.3.1.1 | B8: 1.1. 1 3. 1 1 | C8: 1.1. 1 3. 1 1: REGIMEN ESPECIAL DE IMPUESTO A LA RENTA
A9: 1.1.1.4.1.1 | B9: 1.1. 1 4. 1 1 | C9: 1.1. 1 4. 1 1: REGIMEN PARA LA AMAZONIA
A10: 1.1.1.4.1.2 | B10: 1.1. 1 4. 1 2 | C10: 1.1. 1 4. 1 2: REGIMEN AGRARIO
A11: 1.1.1.4.1.3 | B11: 1.1. 1 4. 1 3 | C11: 1.1. 1 4. 1 3: REGIMEN DE FRONTERA
A12: 1.1.1.5.1.1 | B12: 1.1. 1 5. 1 1 | C12: 1.1. 1 5. 1 1: REGULARIZACION DE IMPUESTO A LA RENTA DE PERSONAS JURIDICAS
... A1529: 2.2.2.1.3.1 | B1529: 2.2. 2 1. 3 1 | C1529: 2.2. 2 1. 3 1: GASTOS DE SEPELIO Y LUTO DEL PERSONAL ACTIVO
